<?xml version="1.0" encoding="utf-8"?><ManagementPack ContentReadable="true" SchemaVersion="2.0" OriginalSchemaVersion="1.1" xmlns:xsd="http://www.w3.org/2001/XMLSchema" xmlns:xsl="http://www.w3.org/1999/XSL/Transform">
  <Manifest>
    <Identity>
      <ID>TestGroup19_ManagementPack</ID>
      <Version>1.0.0.0</Version>
    </Identity>
    <Name>TestGroup19</Name>
    <References>
      <Reference Alias="System_Library">
        <ID>System.Library</ID>
        <Version>7.5.8501.0</Version>
        <PublicKeyToken>31bf3856ad364e35</PublicKeyToken>
      </Reference>
      <Reference Alias="Microsoft_Windows_Library">
        <ID>Microsoft.Windows.Library</ID>
        <Version>7.5.8501.0</Version>
        <PublicKeyToken>31bf3856ad364e35</PublicKeyToken>
      </Reference>
      <Reference Alias="Microsoft_SystemCenter_Library">
        <ID>Microsoft.SystemCenter.Library</ID>
        <Version>7.0.8427.0</Version>
        <PublicKeyToken>31bf3856ad364e35</PublicKeyToken>
      </Reference>
      <Reference Alias="System_WorkItem_Incident_Library">
        <ID>System.WorkItem.Incident.Library</ID>
        <Version>7.5.1561.0</Version>
        <PublicKeyToken>31bf3856ad364e35</PublicKeyToken>
      </Reference>
      <Reference Alias="Microsoft_SystemCenter_InstanceGroup_Library">
        <ID>Microsoft.SystemCenter.InstanceGroup.Library</ID>
        <Version>7.5.8501.0</Version>
        <PublicKeyToken>31bf3856ad364e35</PublicKeyToken>
      </Reference>
      <Reference Alias="System_WorkItem_Library">
        <ID>System.WorkItem.Library</ID>
        <Version>7.5.1561.0</Version>
        <PublicKeyToken>31bf3856ad364e35</PublicKeyToken>
      </Reference>
      <Reference Alias="System_WorkItem_Activity_Library">
        <ID>System.WorkItem.Activity.Library</ID>
        <Version>7.5.1561.0</Version>
        <PublicKeyToken>31bf3856ad364e35</PublicKeyToken>
      </Reference>
      <Reference Alias="System_Notifications_Library">
        <ID>System.Notifications.Library</ID>
        <Version>7.5.1561.0</Version>
        <PublicKeyToken>31bf3856ad364e35</PublicKeyToken>
      </Reference>
      <Reference Alias="System_WorkItem_ChangeRequest_Library">
        <ID>System.WorkItem.ChangeRequest.Library</ID>
        <Version>7.5.1561.0</Version>
        <PublicKeyToken>31bf3856ad364e35</PublicKeyToken>
      </Reference>
      <Reference Alias="System_WorkItem_Problem_Library">
        <ID>System.WorkItem.Problem.Library</ID>
        <Version>7.5.1561.0</Version>
        <PublicKeyToken>31bf3856ad364e35</PublicKeyToken>
      </Reference>
      <Reference Alias="System_WorkItem_ServiceRequest_Library">
        <ID>System.WorkItem.ServiceRequest.Library</ID>
        <Version>7.5.1561.0</Version>
        <PublicKeyToken>31bf3856ad364e35</PublicKeyToken>
      </Reference>
      <Reference Alias="EnterpriseManagement">
        <ID>Microsoft.EnterpriseManagement.ServiceManager.UI.Administration</ID>
        <Version>7.5.1561.0</Version>
        <PublicKeyToken>31bf3856ad364e35</PublicKeyToken>
      </Reference>
      <Reference Alias="SystemCenter">
        <ID>Microsoft.SystemCenter.Subscriptions</ID>
        <Version>7.5.1561.0</Version>
        <PublicKeyToken>31bf3856ad364e35</PublicKeyToken>
      </Reference>
    </References>
  </Manifest>
  <TypeDefinitions>
    <EntityTypes>
      <ClassTypes>
        <ClassType ID="WorkItemGroup.b25073082b7248fcb8e662a4bf8ddefa" Accessibility="Public" Abstract="false" Base="System_WorkItem_Library!System.WorkItemGroup" Hosted="false" Singleton="true" Extension="false" />
        <ClassType ID="WorkItemGroup.024d43e6a155496a91ce2240c1838ebd" Accessibility="Public" Abstract="false" Base="System_WorkItem_Library!System.WorkItemGroup" Hosted="false" Singleton="true" Extension="false" />
        <ClassType ID="WorkItemGroup.e62aaf716b334c28b6526145e5e009af" Accessibility="Public" Abstract="false" Base="System_WorkItem_Library!System.WorkItemGroup" Hosted="false" Singleton="true" Extension="false" />
        <ClassType ID="WorkItemGroup.a56d13d401ff4ac987e656b43ff90b1a" Accessibility="Public" Abstract="false" Base="System_WorkItem_Library!System.WorkItemGroup" Hosted="false" Singleton="true" Extension="false" />
      </ClassTypes>
      <RelationshipTypes>
        <RelationshipType ID="WorkItemGroup.b25073082b7248fcb8e662a4bf8ddefa_Contains_System.WorkItem.Incident" Accessibility="Public" Abstract="false" Base="System_WorkItem_Library!System.WorkItemGroupContainsWorkItems">
          <Source ID="ContainedByGroup" MinCardinality="0" MaxCardinality="2147483647" Type="WorkItemGroup.b25073082b7248fcb8e662a4bf8ddefa" />
          <Target ID="GroupContains" MinCardinality="0" MaxCardinality="2147483647" Type="System_WorkItem_Incident_Library!System.WorkItem.Incident" />
        </RelationshipType>
        <RelationshipType ID="WorkItemGroup.024d43e6a155496a91ce2240c1838ebd_Contains_System.WorkItem.ChangeRequest" Accessibility="Public" Abstract="false" Base="System_WorkItem_Library!System.WorkItemGroupContainsWorkItems">
          <Source ID="ContainedByGroup" MinCardinality="0" MaxCardinality="2147483647" Type="WorkItemGroup.024d43e6a155496a91ce2240c1838ebd" />
          <Target ID="GroupContains" MinCardinality="0" MaxCardinality="2147483647" Type="System_WorkItem_ChangeRequest_Library!System.WorkItem.ChangeRequest" />
        </RelationshipType>
        <RelationshipType ID="WorkItemGroup.e62aaf716b334c28b6526145e5e009af_Contains_System.WorkItem.Problem" Accessibility="Public" Abstract="false" Base="System_WorkItem_Library!System.WorkItemGroupContainsWorkItems">
          <Source ID="ContainedByGroup" MinCardinality="0" MaxCardinality="2147483647" Type="WorkItemGroup.e62aaf716b334c28b6526145e5e009af" />
          <Target ID="GroupContains" MinCardinality="0" MaxCardinality="2147483647" Type="System_WorkItem_Problem_Library!System.WorkItem.Problem" />
        </RelationshipType>
        <RelationshipType ID="WorkItemGroup.a56d13d401ff4ac987e656b43ff90b1a_Contains_System.WorkItem.ServiceRequest" Accessibility="Public" Abstract="false" Base="System_WorkItem_Library!System.WorkItemGroupContainsWorkItems">
          <Source ID="ContainedByGroup" MinCardinality="0" MaxCardinality="2147483647" Type="WorkItemGroup.a56d13d401ff4ac987e656b43ff90b1a" />
          <Target ID="GroupContains" MinCardinality="0" MaxCardinality="2147483647" Type="System_WorkItem_ServiceRequest_Library!System.WorkItem.ServiceRequest" />
        </RelationshipType>
      </RelationshipTypes>
      <EnumerationTypes>
        <EnumerationValue ID="TestGroup19_Enum" Accessibility="Public" Parent="System_WorkItem_Incident_Library!IncidentTierQueuesEnum" Ordinal="19" />
      </EnumerationTypes>
    </EntityTypes>
  </TypeDefinitions>
  <Categories>
    <Category ID="Category.c6a841b7de8b48e5a831bdc48e54459b" Target="NotificationSubscriptiond14c3c32d49e48c69f35c009cd1e0306" Value="EnterpriseManagement!Microsoft.EnterpriseManagement.ServiceManager.Rules.WorkflowSubscriptions" />
    <Category ID="Category.1dcd5854cfd7478994a35486b6a600a0" Target="NotificationSubscription0e4ffda5857d43288ef48722c4718872" Value="EnterpriseManagement!Microsoft.EnterpriseManagement.ServiceManager.Rules.WorkflowSubscriptions" />
    <Category ID="Category.c9a26932c01b4c1e8fce628923b00ca8" Target="NotificationSubscription3c6e8d1f4d6e47bdb46880dfa4fc400e" Value="EnterpriseManagement!Microsoft.EnterpriseManagement.ServiceManager.Rules.WorkflowSubscriptions" />
    <Category ID="Category.4b92994ac46b4453af7df7d42cf284ca" Target="NotificationSubscription4513c2c4831c4eaaaa7fd9cddadb66aa" Value="EnterpriseManagement!Microsoft.EnterpriseManagement.ServiceManager.Rules.WorkflowSubscriptions" />
    <Category ID="Category.8aed39414a45456aa4ffbdfd1f60a8d1" Target="NotificationSubscriptionc669e3f8cbc6450ea4183b93483e8065" Value="EnterpriseManagement!Microsoft.EnterpriseManagement.ServiceManager.Rules.WorkflowSubscriptions" />
    <Category ID="Category.2660237441db4bffadc9c8dd4ed31108" Target="NotificationSubscriptionfcd904595c164b38899e596b3c2208cb" Value="EnterpriseManagement!Microsoft.EnterpriseManagement.ServiceManager.Rules.WorkflowSubscriptions" />
    <Category ID="Category.827e18693aec4eb78b6603282061c85c" Target="NotificationSubscription1f72ca1c306c479189917b830599c491" Value="EnterpriseManagement!Microsoft.EnterpriseManagement.ServiceManager.Rules.WorkflowSubscriptions" />
    <Category ID="Category.480147f34afb4579879d3d4ac70d5d44" Target="NotificationSubscription23a031e309b84857b6d2b8e336e6bd65" Value="EnterpriseManagement!Microsoft.EnterpriseManagement.ServiceManager.Rules.WorkflowSubscriptions" />
    <Category ID="Category.ea98ae8d576545618485b1cbb89cee97" Target="NotificationSubscription2e6528f1c6be49c8ab1cbee4d62de3bc" Value="EnterpriseManagement!Microsoft.EnterpriseManagement.ServiceManager.Rules.WorkflowSubscriptions" />
    <Category ID="Category.fcb793c1b7b8472f8e9769cbe32bf32d" Target="NotificationSubscriptiond3cc7de364b8426c8afcafbebb2f4ab4" Value="EnterpriseManagement!Microsoft.EnterpriseManagement.ServiceManager.Rules.WorkflowSubscriptions" />
    <Category ID="Category.d6b84cfb14a347a3a29d93f2bb497476" Target="NotificationSubscription91abff2e69764a73b2935059f1b30f14" Value="EnterpriseManagement!Microsoft.EnterpriseManagement.ServiceManager.Rules.WorkflowSubscriptions" />
    <Category ID="Category.f8a368d6ddba43f5bc5c9d7f885dd1eb" Target="NotificationSubscription1a9bfc298914480e9ba4db51f31d3c41" Value="EnterpriseManagement!Microsoft.EnterpriseManagement.ServiceManager.Rules.WorkflowSubscriptions" />
    <Category ID="Category.592ad01ef203446f986c51456a479934" Target="NotificationSubscription48f83d7476c44275874d70f325e9bb3d" Value="EnterpriseManagement!Microsoft.EnterpriseManagement.ServiceManager.Rules.WorkflowSubscriptions" />
    <Category ID="Category.54f592f6fbd3438480aa312d5309839a" Target="NotificationSubscription84eb1a03d9ef4098b43a2c99a383a918" Value="EnterpriseManagement!Microsoft.EnterpriseManagement.ServiceManager.Rules.WorkflowSubscriptions" />
  </Categories>
  <Monitoring>
    <Discoveries>
      <Discovery ID="WorkItemGroup.b25073082b7248fcb8e662a4bf8ddefa.Discovery" Enabled="true" Target="WorkItemGroup.b25073082b7248fcb8e662a4bf8ddefa" ConfirmDelivery="false" Remotable="true" Priority="Normal">
        <Category>Discovery</Category>
        <DiscoveryTypes>
          <DiscoveryRelationship TypeID="WorkItemGroup.b25073082b7248fcb8e662a4bf8ddefa_Contains_System.WorkItem.Incident" />
        </DiscoveryTypes>
        <DataSource ID="GroupPopulationDataSource" TypeID="Microsoft_SystemCenter_Library!Microsoft.SystemCenter.GroupPopulator">
          <RuleId>$MPElement$</RuleId>
          <GroupInstanceId>$MPElement[Name="WorkItemGroup.b25073082b7248fcb8e662a4bf8ddefa"]$</GroupInstanceId>
          <MembershipRules>
            <MembershipRule>
              <MonitoringClass>$MPElement[Name="System_WorkItem_Incident_Library!System.WorkItem.Incident"]$</MonitoringClass>
              <RelationshipClass>$MPElement[Name="WorkItemGroup.b25073082b7248fcb8e662a4bf8ddefa_Contains_System.WorkItem.Incident"]$</RelationshipClass>
              <Expression>
                <SimpleExpression>
                  <ValueExpression>
                    <Property>$Context/Property[Type='System_WorkItem_Incident_Library!System.WorkItem.Incident']/TierQueue$</Property>
                  </ValueExpression>
                  <Operator>Equal</Operator>
                  <ValueExpression>
                    <Value>{313ec82a-461b-238e-3269-9f9fa2385fce}</Value>
                  </ValueExpression>
                </SimpleExpression>
              </Expression>
            </MembershipRule>
          </MembershipRules>
        </DataSource>
      </Discovery>
      <Discovery ID="WorkItemGroup.024d43e6a155496a91ce2240c1838ebd.Discovery" Enabled="true" Target="WorkItemGroup.024d43e6a155496a91ce2240c1838ebd" ConfirmDelivery="false" Remotable="true" Priority="Normal">
        <Category>Discovery</Category>
        <DiscoveryTypes>
          <DiscoveryRelationship TypeID="WorkItemGroup.024d43e6a155496a91ce2240c1838ebd_Contains_System.WorkItem.ChangeRequest" />
        </DiscoveryTypes>
        <DataSource ID="GroupPopulationDataSource" TypeID="Microsoft_SystemCenter_Library!Microsoft.SystemCenter.GroupPopulator">
          <RuleId>$MPElement$</RuleId>
          <GroupInstanceId>$MPElement[Name="WorkItemGroup.024d43e6a155496a91ce2240c1838ebd"]$</GroupInstanceId>
          <MembershipRules>
            <MembershipRule>
              <MonitoringClass>$MPElement[Name="System_WorkItem_ChangeRequest_Library!System.WorkItem.ChangeRequest"]$</MonitoringClass>
              <RelationshipClass>$MPElement[Name="WorkItemGroup.024d43e6a155496a91ce2240c1838ebd_Contains_System.WorkItem.ChangeRequest"]$</RelationshipClass>
              <Expression>
                <SimpleExpression>
                  <ValueExpression>
                    <Property>$Context/Property[Type='System_WorkItem_ChangeRequest_Library!System.WorkItem.ChangeRequest']/TierQueue$</Property>
                  </ValueExpression>
                  <Operator>Equal</Operator>
                  <ValueExpression>
                    <Value>{313ec82a-461b-238e-3269-9f9fa2385fce}</Value>
                  </ValueExpression>
                </SimpleExpression>
              </Expression>
            </MembershipRule>
          </MembershipRules>
        </DataSource>
      </Discovery>
      <Discovery ID="WorkItemGroup.e62aaf716b334c28b6526145e5e009af.Discovery" Enabled="true" Target="WorkItemGroup.e62aaf716b334c28b6526145e5e009af" ConfirmDelivery="false" Remotable="true" Priority="Normal">
        <Category>Discovery</Category>
        <DiscoveryTypes>
          <DiscoveryRelationship TypeID="WorkItemGroup.e62aaf716b334c28b6526145e5e009af_Contains_System.WorkItem.Problem" />
        </DiscoveryTypes>
        <DataSource ID="GroupPopulationDataSource" TypeID="Microsoft_SystemCenter_Library!Microsoft.SystemCenter.GroupPopulator">
          <RuleId>$MPElement$</RuleId>
          <GroupInstanceId>$MPElement[Name="WorkItemGroup.e62aaf716b334c28b6526145e5e009af"]$</GroupInstanceId>
          <MembershipRules>
            <MembershipRule>
              <MonitoringClass>$MPElement[Name="System_WorkItem_Problem_Library!System.WorkItem.Problem"]$</MonitoringClass>
              <RelationshipClass>$MPElement[Name="WorkItemGroup.e62aaf716b334c28b6526145e5e009af_Contains_System.WorkItem.Problem"]$</RelationshipClass>
              <Expression>
                <SimpleExpression>
                  <ValueExpression>
                    <Property>$Context/Property[Type='System_WorkItem_Problem_Library!System.WorkItem.Problem']/TierQueue$</Property>
                  </ValueExpression>
                  <Operator>Equal</Operator>
                  <ValueExpression>
                    <Value>{313ec82a-461b-238e-3269-9f9fa2385fce}</Value>
                  </ValueExpression>
                </SimpleExpression>
              </Expression>
            </MembershipRule>
          </MembershipRules>
        </DataSource>
      </Discovery>
      <Discovery ID="WorkItemGroup.a56d13d401ff4ac987e656b43ff90b1a.Discovery" Enabled="true" Target="WorkItemGroup.a56d13d401ff4ac987e656b43ff90b1a" ConfirmDelivery="false" Remotable="true" Priority="Normal">
        <Category>Discovery</Category>
        <DiscoveryTypes>
          <DiscoveryRelationship TypeID="WorkItemGroup.a56d13d401ff4ac987e656b43ff90b1a_Contains_System.WorkItem.ServiceRequest" />
        </DiscoveryTypes>
        <DataSource ID="GroupPopulationDataSource" TypeID="Microsoft_SystemCenter_Library!Microsoft.SystemCenter.GroupPopulator">
          <RuleId>$MPElement$</RuleId>
          <GroupInstanceId>$MPElement[Name="WorkItemGroup.a56d13d401ff4ac987e656b43ff90b1a"]$</GroupInstanceId>
          <MembershipRules>
            <MembershipRule>
              <MonitoringClass>$MPElement[Name="System_WorkItem_ServiceRequest_Library!System.WorkItem.ServiceRequest"]$</MonitoringClass>
              <RelationshipClass>$MPElement[Name="WorkItemGroup.a56d13d401ff4ac987e656b43ff90b1a_Contains_System.WorkItem.ServiceRequest"]$</RelationshipClass>
              <Expression>
                <SimpleExpression>
                  <ValueExpression>
                    <Property>$Context/Property[Type='System_WorkItem_ServiceRequest_Library!System.WorkItem.ServiceRequest']/TierQueue$</Property>
                  </ValueExpression>
                  <Operator>Equal</Operator>
                  <ValueExpression>
                    <Value>{313ec82a-461b-238e-3269-9f9fa2385fce}</Value>
                  </ValueExpression>
                </SimpleExpression>
              </Expression>
            </MembershipRule>
          </MembershipRules>
        </DataSource>
      </Discovery>
    </Discoveries>
    <Rules>
      <Rule ID="NotificationSubscriptiond14c3c32d49e48c69f35c009cd1e0306" Enabled="true" Target="Microsoft_SystemCenter_Library!Microsoft.SystemCenter.SubscriptionWorkflowTarget" ConfirmDelivery="true" Remotable="true" Priority="Normal" DiscardLevel="100">
        <Category>System</Category>
        <DataSources>
          <DataSource ID="DS" TypeID="SystemCenter!Microsoft.SystemCenter.CmdbInstanceSubscription.DataSourceModule">
            <Subscription>
              <InstanceSubscription Type="a604b942-4c7b-2fb2-28dc-61dc6f465c68">
                <AddInstance>
                  <Criteria>
                    <Expression>
                      <SimpleExpression>
                        <ValueExpression>
                          <Property State="Post">$Context/Property[Type='System_WorkItem_Incident_Library!System.WorkItem.Incident']/TierQueue$</Property>
                        </ValueExpression>
                        <Operator>Equal</Operator>
                        <ValueExpression>
                          <Value>{313ec82a-461b-238e-3269-9f9fa2385fce}</Value>
                        </ValueExpression>
                      </SimpleExpression>
                    </Expression>
                  </Criteria>
                </AddInstance>
              </InstanceSubscription>
              <PollingIntervalInSeconds>60</PollingIntervalInSeconds>
              <BatchSize>100</BatchSize>
            </Subscription>
          </DataSource>
        </DataSources>
        <WriteActions>
          <WriteAction ID="WA" TypeID="SystemCenter!Microsoft.EnterpriseManagement.SystemCenter.Subscription.WindowsWorkflowTaskWriteAction">
            <Subscription>
              <VisibleWorkflowStatusUi>true</VisibleWorkflowStatusUi>
              <EnableBatchProcessing>false</EnableBatchProcessing>
              <WindowsWorkflowConfiguration>
                <AssemblyName>Microsoft.EnterpriseManagement.Notifications.Workflows</AssemblyName>
                <WorkflowTypeName>Microsoft.EnterpriseManagement.Notifications.Workflows.SendNotificationsActivity</WorkflowTypeName>
                <WorkflowParameters>
                  <WorkflowParameter Name="SubscriptionId" Type="guid">$MPElement$</WorkflowParameter>
                  <WorkflowParameter Name="DataItem" Type="string">$Data/.$</WorkflowParameter>
                  <WorkflowParameter Name="InstanceId" Type="string">$Data/BaseManagedEntityId$</WorkflowParameter>
                  <WorkflowArrayParameter Name="TemplateIds" Type="string">
                    <Item>5d822e13-666e-d8f6-dd81-ed898a6001ed</Item>
                  </WorkflowArrayParameter>
                  <WorkflowArrayParameter Name="PrimaryUserList" Type="string">
                    <Item>669674d8-bebd-44c9-e6e3-e13e662024f9</Item>
                  </WorkflowArrayParameter>
                </WorkflowParameters>
                <RetryExceptions />
                <RetryDelaySeconds>60</RetryDelaySeconds>
                <MaximumRunningTimeSeconds>7200</MaximumRunningTimeSeconds>
              </WindowsWorkflowConfiguration>
            </Subscription>
          </WriteAction>
        </WriteActions>
      </Rule>
      <Rule ID="NotificationSubscription0e4ffda5857d43288ef48722c4718872" Enabled="true" Target="Microsoft_SystemCenter_Library!Microsoft.SystemCenter.SubscriptionWorkflowTarget" ConfirmDelivery="true" Remotable="true" Priority="Normal" DiscardLevel="100">
        <Category>System</Category>
        <DataSources>
          <DataSource ID="DS" TypeID="SystemCenter!Microsoft.SystemCenter.CmdbInstanceSubscription.DataSourceModule">
            <Subscription>
              <InstanceSubscription Type="a604b942-4c7b-2fb2-28dc-61dc6f465c68">
                <UpdateInstance>
                  <Criteria>
                    <Expression>
                      <SimpleExpression>
                        <ValueExpression>
                          <Property State="Post">$Context/Property[Type='System_WorkItem_Incident_Library!System.WorkItem.Incident']/TierQueue$</Property>
                        </ValueExpression>
                        <Operator>Equal</Operator>
                        <ValueExpression>
                          <Value>{313ec82a-461b-238e-3269-9f9fa2385fce}</Value>
                        </ValueExpression>
                      </SimpleExpression>
                    </Expression>
                  </Criteria>
                </UpdateInstance>
              </InstanceSubscription>
              <PollingIntervalInSeconds>60</PollingIntervalInSeconds>
              <BatchSize>100</BatchSize>
            </Subscription>
          </DataSource>
        </DataSources>
        <WriteActions>
          <WriteAction ID="WA" TypeID="SystemCenter!Microsoft.EnterpriseManagement.SystemCenter.Subscription.WindowsWorkflowTaskWriteAction">
            <Subscription>
              <VisibleWorkflowStatusUi>true</VisibleWorkflowStatusUi>
              <EnableBatchProcessing>false</EnableBatchProcessing>
              <WindowsWorkflowConfiguration>
                <AssemblyName>Microsoft.EnterpriseManagement.Notifications.Workflows</AssemblyName>
                <WorkflowTypeName>Microsoft.EnterpriseManagement.Notifications.Workflows.SendNotificationsActivity</WorkflowTypeName>
                <WorkflowParameters>
                  <WorkflowParameter Name="SubscriptionId" Type="guid">$MPElement$</WorkflowParameter>
                  <WorkflowParameter Name="DataItem" Type="string">$Data/.$</WorkflowParameter>
                  <WorkflowParameter Name="InstanceId" Type="string">$Data/BaseManagedEntityId$</WorkflowParameter>
                  <WorkflowArrayParameter Name="TemplateIds" Type="string">
                    <Item>5d822e13-666e-d8f6-dd81-ed898a6001ed</Item>
                  </WorkflowArrayParameter>
                  <WorkflowArrayParameter Name="PrimaryUserList" Type="string">
                    <Item>669674d8-bebd-44c9-e6e3-e13e662024f9</Item>
                  </WorkflowArrayParameter>
                </WorkflowParameters>
                <RetryExceptions />
                <RetryDelaySeconds>60</RetryDelaySeconds>
                <MaximumRunningTimeSeconds>7200</MaximumRunningTimeSeconds>
              </WindowsWorkflowConfiguration>
            </Subscription>
          </WriteAction>
        </WriteActions>
      </Rule>
      <Rule ID="NotificationSubscription3c6e8d1f4d6e47bdb46880dfa4fc400e" Enabled="true" Target="Microsoft_SystemCenter_Library!Microsoft.SystemCenter.SubscriptionWorkflowTarget" ConfirmDelivery="true" Remotable="true" Priority="Normal" DiscardLevel="100">
        <Category>System</Category>
        <DataSources>
          <DataSource ID="DS" TypeID="SystemCenter!Microsoft.SystemCenter.CmdbInstanceSubscription.DataSourceModule">
            <Subscription>
              <InstanceSubscription Type="e6c9cf6e-d7fe-1b5d-216c-c3f5d2c7670c">
                <AddInstance>
                  <Criteria>
                    <Expression>
                      <SimpleExpression>
                        <ValueExpression>
                          <Property State="Post">$Context/Property[Type='System_WorkItem_ChangeRequest_Library!System.WorkItem.ChangeRequest']/TierQueue$</Property>
                        </ValueExpression>
                        <Operator>Equal</Operator>
                        <ValueExpression>
                          <Value>{313ec82a-461b-238e-3269-9f9fa2385fce}</Value>
                        </ValueExpression>
                      </SimpleExpression>
                    </Expression>
                  </Criteria>
                </AddInstance>
              </InstanceSubscription>
              <PollingIntervalInSeconds>60</PollingIntervalInSeconds>
              <BatchSize>100</BatchSize>
            </Subscription>
          </DataSource>
        </DataSources>
        <WriteActions>
          <WriteAction ID="WA" TypeID="SystemCenter!Microsoft.EnterpriseManagement.SystemCenter.Subscription.WindowsWorkflowTaskWriteAction">
            <Subscription>
              <VisibleWorkflowStatusUi>true</VisibleWorkflowStatusUi>
              <EnableBatchProcessing>false</EnableBatchProcessing>
              <WindowsWorkflowConfiguration>
                <AssemblyName>Microsoft.EnterpriseManagement.Notifications.Workflows</AssemblyName>
                <WorkflowTypeName>Microsoft.EnterpriseManagement.Notifications.Workflows.SendNotificationsActivity</WorkflowTypeName>
                <WorkflowParameters>
                  <WorkflowParameter Name="SubscriptionId" Type="guid">$MPElement$</WorkflowParameter>
                  <WorkflowParameter Name="DataItem" Type="string">$Data/.$</WorkflowParameter>
                  <WorkflowParameter Name="InstanceId" Type="string">$Data/BaseManagedEntityId$</WorkflowParameter>
                  <WorkflowArrayParameter Name="TemplateIds" Type="string">
                    <Item>a733e5da-1591-dcfc-2111-7b2a8da9070f</Item>
                  </WorkflowArrayParameter>
                  <WorkflowArrayParameter Name="PrimaryUserList" Type="string">
                    <Item>669674d8-bebd-44c9-e6e3-e13e662024f9</Item>
                  </WorkflowArrayParameter>
                </WorkflowParameters>
                <RetryExceptions />
                <RetryDelaySeconds>60</RetryDelaySeconds>
                <MaximumRunningTimeSeconds>7200</MaximumRunningTimeSeconds>
              </WindowsWorkflowConfiguration>
            </Subscription>
          </WriteAction>
        </WriteActions>
      </Rule>
      <Rule ID="NotificationSubscription4513c2c4831c4eaaaa7fd9cddadb66aa" Enabled="true" Target="Microsoft_SystemCenter_Library!Microsoft.SystemCenter.SubscriptionWorkflowTarget" ConfirmDelivery="true" Remotable="true" Priority="Normal" DiscardLevel="100">
        <Category>System</Category>
        <DataSources>
          <DataSource ID="DS" TypeID="SystemCenter!Microsoft.SystemCenter.CmdbInstanceSubscription.DataSourceModule">
            <Subscription>
              <InstanceSubscription Type="e6c9cf6e-d7fe-1b5d-216c-c3f5d2c7670c">
                <UpdateInstance>
                  <Criteria>
                    <Expression>
                      <SimpleExpression>
                        <ValueExpression>
                          <Property State="Post">$Context/Property[Type='System_WorkItem_ChangeRequest_Library!System.WorkItem.ChangeRequest']/TierQueue$</Property>
                        </ValueExpression>
                        <Operator>Equal</Operator>
                        <ValueExpression>
                          <Value>{313ec82a-461b-238e-3269-9f9fa2385fce}</Value>
                        </ValueExpression>
                      </SimpleExpression>
                    </Expression>
                  </Criteria>
                </UpdateInstance>
              </InstanceSubscription>
              <PollingIntervalInSeconds>60</PollingIntervalInSeconds>
              <BatchSize>100</BatchSize>
            </Subscription>
          </DataSource>
        </DataSources>
        <WriteActions>
          <WriteAction ID="WA" TypeID="SystemCenter!Microsoft.EnterpriseManagement.SystemCenter.Subscription.WindowsWorkflowTaskWriteAction">
            <Subscription>
              <VisibleWorkflowStatusUi>true</VisibleWorkflowStatusUi>
              <EnableBatchProcessing>false</EnableBatchProcessing>
              <WindowsWorkflowConfiguration>
                <AssemblyName>Microsoft.EnterpriseManagement.Notifications.Workflows</AssemblyName>
                <WorkflowTypeName>Microsoft.EnterpriseManagement.Notifications.Workflows.SendNotificationsActivity</WorkflowTypeName>
                <WorkflowParameters>
                  <WorkflowParameter Name="SubscriptionId" Type="guid">$MPElement$</WorkflowParameter>
                  <WorkflowParameter Name="DataItem" Type="string">$Data/.$</WorkflowParameter>
                  <WorkflowParameter Name="InstanceId" Type="string">$Data/BaseManagedEntityId$</WorkflowParameter>
                  <WorkflowArrayParameter Name="TemplateIds" Type="string">
                    <Item>a733e5da-1591-dcfc-2111-7b2a8da9070f</Item>
                  </WorkflowArrayParameter>
                  <WorkflowArrayParameter Name="PrimaryUserList" Type="string">
                    <Item>669674d8-bebd-44c9-e6e3-e13e662024f9</Item>
                  </WorkflowArrayParameter>
                </WorkflowParameters>
                <RetryExceptions />
                <RetryDelaySeconds>60</RetryDelaySeconds>
                <MaximumRunningTimeSeconds>7200</MaximumRunningTimeSeconds>
              </WindowsWorkflowConfiguration>
            </Subscription>
          </WriteAction>
        </WriteActions>
      </Rule>
      <Rule ID="NotificationSubscriptionc669e3f8cbc6450ea4183b93483e8065" Enabled="true" Target="Microsoft_SystemCenter_Library!Microsoft.SystemCenter.SubscriptionWorkflowTarget" ConfirmDelivery="true" Remotable="true" Priority="Normal" DiscardLevel="100">
        <Category>System</Category>
        <DataSources>
          <DataSource ID="DS" TypeID="SystemCenter!Microsoft.SystemCenter.CmdbInstanceSubscription.DataSourceModule">
            <Subscription>
              <InstanceSubscription Type="422afc88-5eff-f4c5-f8f6-e01038cde67f">
                <AddInstance>
                  <Criteria>
                    <Expression>
                      <SimpleExpression>
                        <ValueExpression>
                          <Property State="Post">$Context/Property[Type='System_WorkItem_Problem_Library!System.WorkItem.Problem']/TierQueue$</Property>
                        </ValueExpression>
                        <Operator>Equal</Operator>
                        <ValueExpression>
                          <Value>{313ec82a-461b-238e-3269-9f9fa2385fce}</Value>
                        </ValueExpression>
                      </SimpleExpression>
                    </Expression>
                  </Criteria>
                </AddInstance>
              </InstanceSubscription>
              <PollingIntervalInSeconds>60</PollingIntervalInSeconds>
              <BatchSize>100</BatchSize>
            </Subscription>
          </DataSource>
        </DataSources>
        <WriteActions>
          <WriteAction ID="WA" TypeID="SystemCenter!Microsoft.EnterpriseManagement.SystemCenter.Subscription.WindowsWorkflowTaskWriteAction">
            <Subscription>
              <VisibleWorkflowStatusUi>true</VisibleWorkflowStatusUi>
              <EnableBatchProcessing>false</EnableBatchProcessing>
              <WindowsWorkflowConfiguration>
                <AssemblyName>Microsoft.EnterpriseManagement.Notifications.Workflows</AssemblyName>
                <WorkflowTypeName>Microsoft.EnterpriseManagement.Notifications.Workflows.SendNotificationsActivity</WorkflowTypeName>
                <WorkflowParameters>
                  <WorkflowParameter Name="SubscriptionId" Type="guid">$MPElement$</WorkflowParameter>
                  <WorkflowParameter Name="DataItem" Type="string">$Data/.$</WorkflowParameter>
                  <WorkflowParameter Name="InstanceId" Type="string">$Data/BaseManagedEntityId$</WorkflowParameter>
                  <WorkflowArrayParameter Name="TemplateIds" Type="string">
                    <Item>18bce03c-089d-8cf7-1214-309192443c77</Item>
                  </WorkflowArrayParameter>
                  <WorkflowArrayParameter Name="PrimaryUserList" Type="string">
                    <Item>669674d8-bebd-44c9-e6e3-e13e662024f9</Item>
                  </WorkflowArrayParameter>
                </WorkflowParameters>
                <RetryExceptions />
                <RetryDelaySeconds>60</RetryDelaySeconds>
                <MaximumRunningTimeSeconds>7200</MaximumRunningTimeSeconds>
              </WindowsWorkflowConfiguration>
            </Subscription>
          </WriteAction>
        </WriteActions>
      </Rule>
      <Rule ID="NotificationSubscriptionfcd904595c164b38899e596b3c2208cb" Enabled="true" Target="Microsoft_SystemCenter_Library!Microsoft.SystemCenter.SubscriptionWorkflowTarget" ConfirmDelivery="true" Remotable="true" Priority="Normal" DiscardLevel="100">
        <Category>System</Category>
        <DataSources>
          <DataSource ID="DS" TypeID="SystemCenter!Microsoft.SystemCenter.CmdbInstanceSubscription.DataSourceModule">
            <Subscription>
              <InstanceSubscription Type="422afc88-5eff-f4c5-f8f6-e01038cde67f">
                <UpdateInstance>
                  <Criteria>
                    <Expression>
                      <SimpleExpression>
                        <ValueExpression>
                          <Property State="Post">$Context/Property[Type='System_WorkItem_Problem_Library!System.WorkItem.Problem']/TierQueue$</Property>
                        </ValueExpression>
                        <Operator>Equal</Operator>
                        <ValueExpression>
                          <Value>{313ec82a-461b-238e-3269-9f9fa2385fce}</Value>
                        </ValueExpression>
                      </SimpleExpression>
                    </Expression>
                  </Criteria>
                </UpdateInstance>
              </InstanceSubscription>
              <PollingIntervalInSeconds>60</PollingIntervalInSeconds>
              <BatchSize>100</BatchSize>
            </Subscription>
          </DataSource>
        </DataSources>
        <WriteActions>
          <WriteAction ID="WA" TypeID="SystemCenter!Microsoft.EnterpriseManagement.SystemCenter.Subscription.WindowsWorkflowTaskWriteAction">
            <Subscription>
              <VisibleWorkflowStatusUi>true</VisibleWorkflowStatusUi>
              <EnableBatchProcessing>false</EnableBatchProcessing>
              <WindowsWorkflowConfiguration>
                <AssemblyName>Microsoft.EnterpriseManagement.Notifications.Workflows</AssemblyName>
                <WorkflowTypeName>Microsoft.EnterpriseManagement.Notifications.Workflows.SendNotificationsActivity</WorkflowTypeName>
                <WorkflowParameters>
                  <WorkflowParameter Name="SubscriptionId" Type="guid">$MPElement$</WorkflowParameter>
                  <WorkflowParameter Name="DataItem" Type="string">$Data/.$</WorkflowParameter>
                  <WorkflowParameter Name="InstanceId" Type="string">$Data/BaseManagedEntityId$</WorkflowParameter>
                  <WorkflowArrayParameter Name="TemplateIds" Type="string">
                    <Item>18bce03c-089d-8cf7-1214-309192443c77</Item>
                  </WorkflowArrayParameter>
                  <WorkflowArrayParameter Name="PrimaryUserList" Type="string">
                    <Item>669674d8-bebd-44c9-e6e3-e13e662024f9</Item>
                  </WorkflowArrayParameter>
                </WorkflowParameters>
                <RetryExceptions />
                <RetryDelaySeconds>60</RetryDelaySeconds>
                <MaximumRunningTimeSeconds>7200</MaximumRunningTimeSeconds>
              </WindowsWorkflowConfiguration>
            </Subscription>
          </WriteAction>
        </WriteActions>
      </Rule>
      <Rule ID="NotificationSubscription1f72ca1c306c479189917b830599c491" Enabled="true" Target="Microsoft_SystemCenter_Library!Microsoft.SystemCenter.SubscriptionWorkflowTarget" ConfirmDelivery="true" Remotable="true" Priority="Normal" DiscardLevel="100">
        <Category>System</Category>
        <DataSources>
          <DataSource ID="DS" TypeID="SystemCenter!Microsoft.SystemCenter.CmdbInstanceSubscription.DataSourceModule">
            <Subscription>
              <InstanceSubscription Type="04b69835-6343-4de2-4b19-6be08c612989">
                <AddInstance>
                  <Criteria>
                    <Expression>
                      <SimpleExpression>
                        <ValueExpression>
                          <Property State="Post">$Context/Property[Type='System_WorkItem_ServiceRequest_Library!System.WorkItem.ServiceRequest']/TierQueue$</Property>
                        </ValueExpression>
                        <Operator>Equal</Operator>
                        <ValueExpression>
                          <Value>{313ec82a-461b-238e-3269-9f9fa2385fce}</Value>
                        </ValueExpression>
                      </SimpleExpression>
                    </Expression>
                  </Criteria>
                </AddInstance>
              </InstanceSubscription>
              <PollingIntervalInSeconds>60</PollingIntervalInSeconds>
              <BatchSize>100</BatchSize>
            </Subscription>
          </DataSource>
        </DataSources>
        <WriteActions>
          <WriteAction ID="WA" TypeID="SystemCenter!Microsoft.EnterpriseManagement.SystemCenter.Subscription.WindowsWorkflowTaskWriteAction">
            <Subscription>
              <VisibleWorkflowStatusUi>true</VisibleWorkflowStatusUi>
              <EnableBatchProcessing>false</EnableBatchProcessing>
              <WindowsWorkflowConfiguration>
                <AssemblyName>Microsoft.EnterpriseManagement.Notifications.Workflows</AssemblyName>
                <WorkflowTypeName>Microsoft.EnterpriseManagement.Notifications.Workflows.SendNotificationsActivity</WorkflowTypeName>
                <WorkflowParameters>
                  <WorkflowParameter Name="SubscriptionId" Type="guid">$MPElement$</WorkflowParameter>
                  <WorkflowParameter Name="DataItem" Type="string">$Data/.$</WorkflowParameter>
                  <WorkflowParameter Name="InstanceId" Type="string">$Data/BaseManagedEntityId$</WorkflowParameter>
                  <WorkflowArrayParameter Name="TemplateIds" Type="string">
                    <Item>6f7884a4-4eed-dc3b-315a-d039cbace3ad</Item>
                  </WorkflowArrayParameter>
                  <WorkflowArrayParameter Name="PrimaryUserList" Type="string">
                    <Item>669674d8-bebd-44c9-e6e3-e13e662024f9</Item>
                  </WorkflowArrayParameter>
                </WorkflowParameters>
                <RetryExceptions />
                <RetryDelaySeconds>60</RetryDelaySeconds>
                <MaximumRunningTimeSeconds>7200</MaximumRunningTimeSeconds>
              </WindowsWorkflowConfiguration>
            </Subscription>
          </WriteAction>
        </WriteActions>
      </Rule>
      <Rule ID="NotificationSubscription23a031e309b84857b6d2b8e336e6bd65" Enabled="true" Target="Microsoft_SystemCenter_Library!Microsoft.SystemCenter.SubscriptionWorkflowTarget" ConfirmDelivery="true" Remotable="true" Priority="Normal" DiscardLevel="100">
        <Category>System</Category>
        <DataSources>
          <DataSource ID="DS" TypeID="SystemCenter!Microsoft.SystemCenter.CmdbInstanceSubscription.DataSourceModule">
            <Subscription>
              <InstanceSubscription Type="04b69835-6343-4de2-4b19-6be08c612989">
                <UpdateInstance>
                  <Criteria>
                    <Expression>
                      <SimpleExpression>
                        <ValueExpression>
                          <Property State="Post">$Context/Property[Type='System_WorkItem_ServiceRequest_Library!System.WorkItem.ServiceRequest']/TierQueue$</Property>
                        </ValueExpression>
                        <Operator>Equal</Operator>
                        <ValueExpression>
                          <Value>{313ec82a-461b-238e-3269-9f9fa2385fce}</Value>
                        </ValueExpression>
                      </SimpleExpression>
                    </Expression>
                  </Criteria>
                </UpdateInstance>
              </InstanceSubscription>
              <PollingIntervalInSeconds>60</PollingIntervalInSeconds>
              <BatchSize>100</BatchSize>
            </Subscription>
          </DataSource>
        </DataSources>
        <WriteActions>
          <WriteAction ID="WA" TypeID="SystemCenter!Microsoft.EnterpriseManagement.SystemCenter.Subscription.WindowsWorkflowTaskWriteAction">
            <Subscription>
              <VisibleWorkflowStatusUi>true</VisibleWorkflowStatusUi>
              <EnableBatchProcessing>false</EnableBatchProcessing>
              <WindowsWorkflowConfiguration>
                <AssemblyName>Microsoft.EnterpriseManagement.Notifications.Workflows</AssemblyName>
                <WorkflowTypeName>Microsoft.EnterpriseManagement.Notifications.Workflows.SendNotificationsActivity</WorkflowTypeName>
                <WorkflowParameters>
                  <WorkflowParameter Name="SubscriptionId" Type="guid">$MPElement$</WorkflowParameter>
                  <WorkflowParameter Name="DataItem" Type="string">$Data/.$</WorkflowParameter>
                  <WorkflowParameter Name="InstanceId" Type="string">$Data/BaseManagedEntityId$</WorkflowParameter>
                  <WorkflowArrayParameter Name="TemplateIds" Type="string">
                    <Item>6f7884a4-4eed-dc3b-315a-d039cbace3ad</Item>
                  </WorkflowArrayParameter>
                  <WorkflowArrayParameter Name="PrimaryUserList" Type="string">
                    <Item>669674d8-bebd-44c9-e6e3-e13e662024f9</Item>
                  </WorkflowArrayParameter>
                </WorkflowParameters>
                <RetryExceptions />
                <RetryDelaySeconds>60</RetryDelaySeconds>
                <MaximumRunningTimeSeconds>7200</MaximumRunningTimeSeconds>
              </WindowsWorkflowConfiguration>
            </Subscription>
          </WriteAction>
        </WriteActions>
      </Rule>
      <Rule ID="NotificationSubscription2e6528f1c6be49c8ab1cbee4d62de3bc" Enabled="true" Target="Microsoft_SystemCenter_Library!Microsoft.SystemCenter.SubscriptionWorkflowTarget" ConfirmDelivery="true" Remotable="true" Priority="Normal" DiscardLevel="100">
        <Category>System</Category>
        <DataSources>
          <DataSource ID="DS" TypeID="SystemCenter!Microsoft.SystemCenter.CmdbInstanceSubscription.DataSourceModule">
            <Subscription>
              <InstanceSubscription Type="04b69835-6343-4de2-4b19-6be08c612989">
                <UpdateInstance>
                  <Criteria>
                    <Expression>
                      <SimpleExpression>
                        <ValueExpression>
                          <Property State="Post">$Context/Property[Type='System_WorkItem_ServiceRequest_Library!System.WorkItem.ServiceRequest']/Status$</Property>
                        </ValueExpression>
                        <Operator>Equal</Operator>
                        <ValueExpression>
                          <Value>{b026fdfd-89bd-490b-e1fd-a599c78d440f}</Value>
                        </ValueExpression>
                      </SimpleExpression>
                    </Expression>
                  </Criteria>
                </UpdateInstance>
              </InstanceSubscription>
              <PollingIntervalInSeconds>60</PollingIntervalInSeconds>
              <BatchSize>100</BatchSize>
            </Subscription>
          </DataSource>
        </DataSources>
        <WriteActions>
          <WriteAction ID="WA" TypeID="SystemCenter!Microsoft.EnterpriseManagement.SystemCenter.Subscription.WindowsWorkflowTaskWriteAction">
            <Subscription>
              <VisibleWorkflowStatusUi>true</VisibleWorkflowStatusUi>
              <EnableBatchProcessing>false</EnableBatchProcessing>
              <WindowsWorkflowConfiguration>
                <AssemblyName>Microsoft.EnterpriseManagement.Notifications.Workflows</AssemblyName>
                <WorkflowTypeName>Microsoft.EnterpriseManagement.Notifications.Workflows.SendNotificationsActivity</WorkflowTypeName>
                <WorkflowParameters>
                  <WorkflowParameter Name="SubscriptionId" Type="guid">$MPElement$</WorkflowParameter>
                  <WorkflowParameter Name="DataItem" Type="string">$Data/.$</WorkflowParameter>
                  <WorkflowParameter Name="InstanceId" Type="string">$Data/BaseManagedEntityId$</WorkflowParameter>
                  <WorkflowArrayParameter Name="TemplateIds" Type="string">
                    <Item>6f7884a4-4eed-dc3b-315a-d039cbace3ad</Item>
                  </WorkflowArrayParameter>
                  <WorkflowArrayParameter Name="PrimaryUserList" Type="string">
                    <Item>669674d8-bebd-44c9-e6e3-e13e662024f9</Item>
                  </WorkflowArrayParameter>
                </WorkflowParameters>
                <RetryExceptions />
                <RetryDelaySeconds>60</RetryDelaySeconds>
                <MaximumRunningTimeSeconds>7200</MaximumRunningTimeSeconds>
              </WindowsWorkflowConfiguration>
            </Subscription>
          </WriteAction>
        </WriteActions>
      </Rule>
      <Rule ID="NotificationSubscriptiond3cc7de364b8426c8afcafbebb2f4ab4" Enabled="true" Target="Microsoft_SystemCenter_Library!Microsoft.SystemCenter.SubscriptionWorkflowTarget" ConfirmDelivery="true" Remotable="true" Priority="Normal" DiscardLevel="100">
        <Category>System</Category>
        <DataSources>
          <DataSource ID="DS" TypeID="SystemCenter!Microsoft.SystemCenter.CmdbInstanceSubscription.DataSourceModule">
            <Subscription>
              <InstanceSubscription Type="04b69835-6343-4de2-4b19-6be08c612989">
                <UpdateInstance>
                  <Criteria>
                    <Expression>
                      <SimpleExpression>
                        <ValueExpression>
                          <Property State="Post">$Context/Property[Type='System_WorkItem_ServiceRequest_Library!System.WorkItem.ServiceRequest']/Status$</Property>
                        </ValueExpression>
                        <Operator>Equal</Operator>
                        <ValueExpression>
                          <Value>{c7b65747-f99e-c108-1e17-3c1062138fc4}</Value>
                        </ValueExpression>
                      </SimpleExpression>
                    </Expression>
                  </Criteria>
                </UpdateInstance>
              </InstanceSubscription>
              <PollingIntervalInSeconds>60</PollingIntervalInSeconds>
              <BatchSize>100</BatchSize>
            </Subscription>
          </DataSource>
        </DataSources>
        <WriteActions>
          <WriteAction ID="WA" TypeID="SystemCenter!Microsoft.EnterpriseManagement.SystemCenter.Subscription.WindowsWorkflowTaskWriteAction">
            <Subscription>
              <VisibleWorkflowStatusUi>true</VisibleWorkflowStatusUi>
              <EnableBatchProcessing>false</EnableBatchProcessing>
              <WindowsWorkflowConfiguration>
                <AssemblyName>Microsoft.EnterpriseManagement.Notifications.Workflows</AssemblyName>
                <WorkflowTypeName>Microsoft.EnterpriseManagement.Notifications.Workflows.SendNotificationsActivity</WorkflowTypeName>
                <WorkflowParameters>
                  <WorkflowParameter Name="SubscriptionId" Type="guid">$MPElement$</WorkflowParameter>
                  <WorkflowParameter Name="DataItem" Type="string">$Data/.$</WorkflowParameter>
                  <WorkflowParameter Name="InstanceId" Type="string">$Data/BaseManagedEntityId$</WorkflowParameter>
                  <WorkflowArrayParameter Name="TemplateIds" Type="string">
                    <Item>6f7884a4-4eed-dc3b-315a-d039cbace3ad</Item>
                  </WorkflowArrayParameter>
                  <WorkflowArrayParameter Name="PrimaryUserList" Type="string">
                    <Item>669674d8-bebd-44c9-e6e3-e13e662024f9</Item>
                  </WorkflowArrayParameter>
                </WorkflowParameters>
                <RetryExceptions />
                <RetryDelaySeconds>60</RetryDelaySeconds>
                <MaximumRunningTimeSeconds>7200</MaximumRunningTimeSeconds>
              </WindowsWorkflowConfiguration>
            </Subscription>
          </WriteAction>
        </WriteActions>
      </Rule>
      <Rule ID="NotificationSubscription91abff2e69764a73b2935059f1b30f14" Enabled="true" Target="Microsoft_SystemCenter_Library!Microsoft.SystemCenter.SubscriptionWorkflowTarget" ConfirmDelivery="true" Remotable="true" Priority="Normal" DiscardLevel="100">
        <Category>System</Category>
        <DataSources>
          <DataSource ID="DS" TypeID="SystemCenter!Microsoft.SystemCenter.CmdbInstanceSubscription.DataSourceModule">
            <Subscription>
              <InstanceSubscription Type="e6c9cf6e-d7fe-1b5d-216c-c3f5d2c7670c">
                <UpdateInstance>
                  <Criteria>
                    <Expression>
                      <SimpleExpression>
                        <ValueExpression>
                          <Property State="Post">$Context/Property[Type='System_WorkItem_ChangeRequest_Library!System.WorkItem.ChangeRequest']/Status$</Property>
                        </ValueExpression>
                        <Operator>Equal</Operator>
                        <ValueExpression>
                          <Value>{68277330-a0d3-cfdd-298d-d5c31d1d126f}</Value>
                        </ValueExpression>
                      </SimpleExpression>
                    </Expression>
                  </Criteria>
                </UpdateInstance>
              </InstanceSubscription>
              <PollingIntervalInSeconds>60</PollingIntervalInSeconds>
              <BatchSize>100</BatchSize>
            </Subscription>
          </DataSource>
        </DataSources>
        <WriteActions>
          <WriteAction ID="WA" TypeID="SystemCenter!Microsoft.EnterpriseManagement.SystemCenter.Subscription.WindowsWorkflowTaskWriteAction">
            <Subscription>
              <VisibleWorkflowStatusUi>true</VisibleWorkflowStatusUi>
              <EnableBatchProcessing>false</EnableBatchProcessing>
              <WindowsWorkflowConfiguration>
                <AssemblyName>Microsoft.EnterpriseManagement.Notifications.Workflows</AssemblyName>
                <WorkflowTypeName>Microsoft.EnterpriseManagement.Notifications.Workflows.SendNotificationsActivity</WorkflowTypeName>
                <WorkflowParameters>
                  <WorkflowParameter Name="SubscriptionId" Type="guid">$MPElement$</WorkflowParameter>
                  <WorkflowParameter Name="DataItem" Type="string">$Data/.$</WorkflowParameter>
                  <WorkflowParameter Name="InstanceId" Type="string">$Data/BaseManagedEntityId$</WorkflowParameter>
                  <WorkflowArrayParameter Name="TemplateIds" Type="string">
                    <Item>a733e5da-1591-dcfc-2111-7b2a8da9070f</Item>
                  </WorkflowArrayParameter>
                  <WorkflowArrayParameter Name="PrimaryUserList" Type="string">
                    <Item>669674d8-bebd-44c9-e6e3-e13e662024f9</Item>
                  </WorkflowArrayParameter>
                </WorkflowParameters>
                <RetryExceptions />
                <RetryDelaySeconds>60</RetryDelaySeconds>
                <MaximumRunningTimeSeconds>7200</MaximumRunningTimeSeconds>
              </WindowsWorkflowConfiguration>
            </Subscription>
          </WriteAction>
        </WriteActions>
      </Rule>
      <Rule ID="NotificationSubscription1a9bfc298914480e9ba4db51f31d3c41" Enabled="true" Target="Microsoft_SystemCenter_Library!Microsoft.SystemCenter.SubscriptionWorkflowTarget" ConfirmDelivery="true" Remotable="true" Priority="Normal" DiscardLevel="100">
        <Category>System</Category>
        <DataSources>
          <DataSource ID="DS" TypeID="SystemCenter!Microsoft.SystemCenter.CmdbInstanceSubscription.DataSourceModule">
            <Subscription>
              <InstanceSubscription Type="e6c9cf6e-d7fe-1b5d-216c-c3f5d2c7670c">
                <UpdateInstance>
                  <Criteria>
                    <Expression>
                      <SimpleExpression>
                        <ValueExpression>
                          <Property State="Post">$Context/Property[Type='System_WorkItem_ChangeRequest_Library!System.WorkItem.ChangeRequest']/Status$</Property>
                        </ValueExpression>
                        <Operator>Equal</Operator>
                        <ValueExpression>
                          <Value>{f228d50b-2b5a-010f-b1a4-5c7d95703a9b}</Value>
                        </ValueExpression>
                      </SimpleExpression>
                    </Expression>
                  </Criteria>
                </UpdateInstance>
              </InstanceSubscription>
              <PollingIntervalInSeconds>60</PollingIntervalInSeconds>
              <BatchSize>100</BatchSize>
            </Subscription>
          </DataSource>
        </DataSources>
        <WriteActions>
          <WriteAction ID="WA" TypeID="SystemCenter!Microsoft.EnterpriseManagement.SystemCenter.Subscription.WindowsWorkflowTaskWriteAction">
            <Subscription>
              <VisibleWorkflowStatusUi>true</VisibleWorkflowStatusUi>
              <EnableBatchProcessing>false</EnableBatchProcessing>
              <WindowsWorkflowConfiguration>
                <AssemblyName>Microsoft.EnterpriseManagement.Notifications.Workflows</AssemblyName>
                <WorkflowTypeName>Microsoft.EnterpriseManagement.Notifications.Workflows.SendNotificationsActivity</WorkflowTypeName>
                <WorkflowParameters>
                  <WorkflowParameter Name="SubscriptionId" Type="guid">$MPElement$</WorkflowParameter>
                  <WorkflowParameter Name="DataItem" Type="string">$Data/.$</WorkflowParameter>
                  <WorkflowParameter Name="InstanceId" Type="string">$Data/BaseManagedEntityId$</WorkflowParameter>
                  <WorkflowArrayParameter Name="TemplateIds" Type="string">
                    <Item>a733e5da-1591-dcfc-2111-7b2a8da9070f</Item>
                  </WorkflowArrayParameter>
                  <WorkflowArrayParameter Name="PrimaryUserList" Type="string">
                    <Item>669674d8-bebd-44c9-e6e3-e13e662024f9</Item>
                  </WorkflowArrayParameter>
                </WorkflowParameters>
                <RetryExceptions />
                <RetryDelaySeconds>60</RetryDelaySeconds>
                <MaximumRunningTimeSeconds>7200</MaximumRunningTimeSeconds>
              </WindowsWorkflowConfiguration>
            </Subscription>
          </WriteAction>
        </WriteActions>
      </Rule>
      <Rule ID="NotificationSubscription48f83d7476c44275874d70f325e9bb3d" Enabled="true" Target="Microsoft_SystemCenter_Library!Microsoft.SystemCenter.SubscriptionWorkflowTarget" ConfirmDelivery="true" Remotable="true" Priority="Normal" DiscardLevel="100">
        <Category>System</Category>
        <DataSources>
          <DataSource ID="DS" TypeID="SystemCenter!Microsoft.SystemCenter.CmdbInstanceSubscription.DataSourceModule">
            <Subscription>
              <InstanceSubscription Type="a604b942-4c7b-2fb2-28dc-61dc6f465c68">
                <UpdateInstance>
                  <Criteria>
                    <Expression>
                      <SimpleExpression>
                        <ValueExpression>
                          <Property State="Post">$Context/Property[Type='System_WorkItem_Incident_Library!System.WorkItem.Incident']/Status$</Property>
                        </ValueExpression>
                        <Operator>Equal</Operator>
                        <ValueExpression>
                          <Value>{2b8830b6-59f0-f574-9c2a-f4b4682f1681}</Value>
                        </ValueExpression>
                      </SimpleExpression>
                    </Expression>
                  </Criteria>
                </UpdateInstance>
              </InstanceSubscription>
              <PollingIntervalInSeconds>60</PollingIntervalInSeconds>
              <BatchSize>100</BatchSize>
            </Subscription>
          </DataSource>
        </DataSources>
        <WriteActions>
          <WriteAction ID="WA" TypeID="SystemCenter!Microsoft.EnterpriseManagement.SystemCenter.Subscription.WindowsWorkflowTaskWriteAction">
            <Subscription>
              <VisibleWorkflowStatusUi>true</VisibleWorkflowStatusUi>
              <EnableBatchProcessing>false</EnableBatchProcessing>
              <WindowsWorkflowConfiguration>
                <AssemblyName>Microsoft.EnterpriseManagement.Notifications.Workflows</AssemblyName>
                <WorkflowTypeName>Microsoft.EnterpriseManagement.Notifications.Workflows.SendNotificationsActivity</WorkflowTypeName>
                <WorkflowParameters>
                  <WorkflowParameter Name="SubscriptionId" Type="guid">$MPElement$</WorkflowParameter>
                  <WorkflowParameter Name="DataItem" Type="string">$Data/.$</WorkflowParameter>
                  <WorkflowParameter Name="InstanceId" Type="string">$Data/BaseManagedEntityId$</WorkflowParameter>
                  <WorkflowArrayParameter Name="TemplateIds" Type="string">
                    <Item>5d822e13-666e-d8f6-dd81-ed898a6001ed</Item>
                  </WorkflowArrayParameter>
                  <WorkflowArrayParameter Name="PrimaryUserList" Type="string">
                    <Item>669674d8-bebd-44c9-e6e3-e13e662024f9</Item>
                  </WorkflowArrayParameter>
                </WorkflowParameters>
                <RetryExceptions />
                <RetryDelaySeconds>60</RetryDelaySeconds>
                <MaximumRunningTimeSeconds>7200</MaximumRunningTimeSeconds>
              </WindowsWorkflowConfiguration>
            </Subscription>
          </WriteAction>
        </WriteActions>
      </Rule>
      <Rule ID="NotificationSubscription84eb1a03d9ef4098b43a2c99a383a918" Enabled="true" Target="Microsoft_SystemCenter_Library!Microsoft.SystemCenter.SubscriptionWorkflowTarget" ConfirmDelivery="true" Remotable="true" Priority="Normal" DiscardLevel="100">
        <Category>System</Category>
        <DataSources>
          <DataSource ID="DS" TypeID="SystemCenter!Microsoft.SystemCenter.CmdbInstanceSubscription.DataSourceModule">
            <Subscription>
              <InstanceSubscription Type="a604b942-4c7b-2fb2-28dc-61dc6f465c68">
                <UpdateInstance>
                  <Criteria>
                    <Expression>
                      <SimpleExpression>
                        <ValueExpression>
                          <Property State="Post">$Context/Property[Type='System_WorkItem_Incident_Library!System.WorkItem.Incident']/Status$</Property>
                        </ValueExpression>
                        <Operator>Equal</Operator>
                        <ValueExpression>
                          <Value>{bd0ae7c4-3315-2eb3-7933-82dfc482dbaf}</Value>
                        </ValueExpression>
                      </SimpleExpression>
                    </Expression>
                  </Criteria>
                </UpdateInstance>
              </InstanceSubscription>
              <PollingIntervalInSeconds>60</PollingIntervalInSeconds>
              <BatchSize>100</BatchSize>
            </Subscription>
          </DataSource>
        </DataSources>
        <WriteActions>
          <WriteAction ID="WA" TypeID="SystemCenter!Microsoft.EnterpriseManagement.SystemCenter.Subscription.WindowsWorkflowTaskWriteAction">
            <Subscription>
              <VisibleWorkflowStatusUi>true</VisibleWorkflowStatusUi>
              <EnableBatchProcessing>false</EnableBatchProcessing>
              <WindowsWorkflowConfiguration>
                <AssemblyName>Microsoft.EnterpriseManagement.Notifications.Workflows</AssemblyName>
                <WorkflowTypeName>Microsoft.EnterpriseManagement.Notifications.Workflows.SendNotificationsActivity</WorkflowTypeName>
                <WorkflowParameters>
                  <WorkflowParameter Name="SubscriptionId" Type="guid">$MPElement$</WorkflowParameter>
                  <WorkflowParameter Name="DataItem" Type="string">$Data/.$</WorkflowParameter>
                  <WorkflowParameter Name="InstanceId" Type="string">$Data/BaseManagedEntityId$</WorkflowParameter>
                  <WorkflowArrayParameter Name="TemplateIds" Type="string">
                    <Item>5d822e13-666e-d8f6-dd81-ed898a6001ed</Item>
                  </WorkflowArrayParameter>
                  <WorkflowArrayParameter Name="PrimaryUserList" Type="string">
                    <Item>669674d8-bebd-44c9-e6e3-e13e662024f9</Item>
                  </WorkflowArrayParameter>
                </WorkflowParameters>
                <RetryExceptions />
                <RetryDelaySeconds>60</RetryDelaySeconds>
                <MaximumRunningTimeSeconds>7200</MaximumRunningTimeSeconds>
              </WindowsWorkflowConfiguration>
            </Subscription>
          </WriteAction>
        </WriteActions>
      </Rule>
    </Rules>
  </Monitoring>
  <LanguagePacks>
    <LanguagePack ID="ENU" IsDefault="true">
      <DisplayStrings>
        <DisplayString ElementID="WorkItemGroup.a56d13d401ff4ac987e656b43ff90b1a">
          <Name>TestGroup19-SR</Name>
        </DisplayString>
        <DisplayString ElementID="WorkItemGroup.a56d13d401ff4ac987e656b43ff90b1a.Discovery">
          <Name>TestGroup19-SR_Discovery</Name>
          <Description>Discovery for Group TestGroup19-SR</Description>
        </DisplayString>
        <DisplayString ElementID="NotificationSubscriptiond14c3c32d49e48c69f35c009cd1e0306">
          <Name>TestGroup19-IN-C</Name>
        </DisplayString>
        <DisplayString ElementID="NotificationSubscription0e4ffda5857d43288ef48722c4718872">
          <Name>TestGroup19-IN-U</Name>
        </DisplayString>
        <DisplayString ElementID="NotificationSubscription3c6e8d1f4d6e47bdb46880dfa4fc400e">
          <Name>TestGroup19-CR-C</Name>
        </DisplayString>
        <DisplayString ElementID="NotificationSubscription4513c2c4831c4eaaaa7fd9cddadb66aa">
          <Name>TestGroup19-CR-U</Name>
        </DisplayString>
        <DisplayString ElementID="NotificationSubscriptionc669e3f8cbc6450ea4183b93483e8065">
          <Name>TestGroup19-PR-C</Name>
        </DisplayString>
        <DisplayString ElementID="NotificationSubscriptionfcd904595c164b38899e596b3c2208cb">
          <Name>TestGroup19-PR-U</Name>
        </DisplayString>
        <DisplayString ElementID="NotificationSubscription1f72ca1c306c479189917b830599c491">
          <Name>TestGroup19-SR-C</Name>
        </DisplayString>
        <DisplayString ElementID="NotificationSubscription23a031e309b84857b6d2b8e336e6bd65">
          <Name>TestGroup19-SR-U</Name>
        </DisplayString>
        <DisplayString ElementID="NotificationSubscription2e6528f1c6be49c8ab1cbee4d62de3bc">
          <Name>TestGroup19-SR-U-Completed</Name>
        </DisplayString>
        <DisplayString ElementID="NotificationSubscriptiond3cc7de364b8426c8afcafbebb2f4ab4">
          <Name>TestGroup19-SR-U-Closed</Name>
        </DisplayString>
        <DisplayString ElementID="NotificationSubscription91abff2e69764a73b2935059f1b30f14">
          <Name>TestGroup19-CR-U-Completed</Name>
        </DisplayString>
        <DisplayString ElementID="NotificationSubscription1a9bfc298914480e9ba4db51f31d3c41">
          <Name>TestGroup19-CR-U-Closed</Name>
        </DisplayString>
        <DisplayString ElementID="NotificationSubscription48f83d7476c44275874d70f325e9bb3d">
          <Name>TestGroup19-IN-U-Resolved</Name>
        </DisplayString>
        <DisplayString ElementID="NotificationSubscription84eb1a03d9ef4098b43a2c99a383a918">
          <Name>TestGroup19-IN-U-Closed</Name>
        </DisplayString>
      </DisplayStrings>
    </LanguagePack>
  </LanguagePacks>
</ManagementPack>