<?xml version="1.0" encoding="utf-8"?><ManagementPack ContentReadable="true" SchemaVersion="2.0" OriginalSchemaVersion="1.1" xmlns:xsd="http://www.w3.org/2001/XMLSchema" xmlns:xsl="http://www.w3.org/1999/XSL/Transform">
  <Manifest>
    <Identity>
      <ID>TestGroup106_ManagementPack</ID>
      <Version>1.0.0.0</Version>
    </Identity>
    <Name>TestGroup106</Name>
    <References>
      <Reference Alias="System_Library">
        <ID>System.Library</ID>
        <Version>7.5.8501.0</Version>
        <PublicKeyToken>31bf3856ad364e35</PublicKeyToken>
      </Reference>
      <Reference Alias="Microsoft_Windows_Library">
        <ID>Microsoft.Windows.Library</ID>
        <Version>7.5.8501.0</Version>
        <PublicKeyToken>31bf3856ad364e35</PublicKeyToken>
      </Reference>
      <Reference Alias="Microsoft_SystemCenter_Library">
        <ID>Microsoft.SystemCenter.Library</ID>
        <Version>7.0.8427.0</Version>
        <PublicKeyToken>31bf3856ad364e35</PublicKeyToken>
      </Reference>
      <Reference Alias="System_WorkItem_Incident_Library">
        <ID>System.WorkItem.Incident.Library</ID>
        <Version>7.5.1561.0</Version>
        <PublicKeyToken>31bf3856ad364e35</PublicKeyToken>
      </Reference>
      <Reference Alias="Microsoft_SystemCenter_InstanceGroup_Library">
        <ID>Microsoft.SystemCenter.InstanceGroup.Library</ID>
        <Version>7.5.8501.0</Version>
        <PublicKeyToken>31bf3856ad364e35</PublicKeyToken>
      </Reference>
      <Reference Alias="System_WorkItem_Library">
        <ID>System.WorkItem.Library</ID>
        <Version>7.5.1561.0</Version>
        <PublicKeyToken>31bf3856ad364e35</PublicKeyToken>
      </Reference>
      <Reference Alias="System_WorkItem_Activity_Library">
        <ID>System.WorkItem.Activity.Library</ID>
        <Version>7.5.1561.0</Version>
        <PublicKeyToken>31bf3856ad364e35</PublicKeyToken>
      </Reference>
      <Reference Alias="System_Notifications_Library">
        <ID>System.Notifications.Library</ID>
        <Version>7.5.1561.0</Version>
        <PublicKeyToken>31bf3856ad364e35</PublicKeyToken>
      </Reference>
      <Reference Alias="System_WorkItem_ChangeRequest_Library">
        <ID>System.WorkItem.ChangeRequest.Library</ID>
        <Version>7.5.1561.0</Version>
        <PublicKeyToken>31bf3856ad364e35</PublicKeyToken>
      </Reference>
      <Reference Alias="System_WorkItem_Problem_Library">
        <ID>System.WorkItem.Problem.Library</ID>
        <Version>7.5.1561.0</Version>
        <PublicKeyToken>31bf3856ad364e35</PublicKeyToken>
      </Reference>
      <Reference Alias="System_WorkItem_ServiceRequest_Library">
        <ID>System.WorkItem.ServiceRequest.Library</ID>
        <Version>7.5.1561.0</Version>
        <PublicKeyToken>31bf3856ad364e35</PublicKeyToken>
      </Reference>
      <Reference Alias="EnterpriseManagement">
        <ID>Microsoft.EnterpriseManagement.ServiceManager.UI.Administration</ID>
        <Version>7.5.1561.0</Version>
        <PublicKeyToken>31bf3856ad364e35</PublicKeyToken>
      </Reference>
      <Reference Alias="SystemCenter">
        <ID>Microsoft.SystemCenter.Subscriptions</ID>
        <Version>7.5.1561.0</Version>
        <PublicKeyToken>31bf3856ad364e35</PublicKeyToken>
      </Reference>
    </References>
  </Manifest>
  <TypeDefinitions>
    <EntityTypes>
      <ClassTypes>
        <ClassType ID="WorkItemGroup.e690c6be0f524fc48de129b80982f39d" Accessibility="Public" Abstract="false" Base="System_WorkItem_Library!System.WorkItemGroup" Hosted="false" Singleton="true" Extension="false" />
        <ClassType ID="WorkItemGroup.43216343a63c404f8be26c0f59cbee03" Accessibility="Public" Abstract="false" Base="System_WorkItem_Library!System.WorkItemGroup" Hosted="false" Singleton="true" Extension="false" />
        <ClassType ID="WorkItemGroup.7245d0f8a5984b5bb557f7cc1baac603" Accessibility="Public" Abstract="false" Base="System_WorkItem_Library!System.WorkItemGroup" Hosted="false" Singleton="true" Extension="false" />
        <ClassType ID="WorkItemGroup.3a962c1115fc4c9782510df178aae29c" Accessibility="Public" Abstract="false" Base="System_WorkItem_Library!System.WorkItemGroup" Hosted="false" Singleton="true" Extension="false" />
      </ClassTypes>
      <RelationshipTypes>
        <RelationshipType ID="WorkItemGroup.e690c6be0f524fc48de129b80982f39d_Contains_System.WorkItem.Incident" Accessibility="Public" Abstract="false" Base="System_WorkItem_Library!System.WorkItemGroupContainsWorkItems">
          <Source ID="ContainedByGroup" MinCardinality="0" MaxCardinality="2147483647" Type="WorkItemGroup.e690c6be0f524fc48de129b80982f39d" />
          <Target ID="GroupContains" MinCardinality="0" MaxCardinality="2147483647" Type="System_WorkItem_Incident_Library!System.WorkItem.Incident" />
        </RelationshipType>
        <RelationshipType ID="WorkItemGroup.43216343a63c404f8be26c0f59cbee03_Contains_System.WorkItem.ChangeRequest" Accessibility="Public" Abstract="false" Base="System_WorkItem_Library!System.WorkItemGroupContainsWorkItems">
          <Source ID="ContainedByGroup" MinCardinality="0" MaxCardinality="2147483647" Type="WorkItemGroup.43216343a63c404f8be26c0f59cbee03" />
          <Target ID="GroupContains" MinCardinality="0" MaxCardinality="2147483647" Type="System_WorkItem_ChangeRequest_Library!System.WorkItem.ChangeRequest" />
        </RelationshipType>
        <RelationshipType ID="WorkItemGroup.7245d0f8a5984b5bb557f7cc1baac603_Contains_System.WorkItem.Problem" Accessibility="Public" Abstract="false" Base="System_WorkItem_Library!System.WorkItemGroupContainsWorkItems">
          <Source ID="ContainedByGroup" MinCardinality="0" MaxCardinality="2147483647" Type="WorkItemGroup.7245d0f8a5984b5bb557f7cc1baac603" />
          <Target ID="GroupContains" MinCardinality="0" MaxCardinality="2147483647" Type="System_WorkItem_Problem_Library!System.WorkItem.Problem" />
        </RelationshipType>
        <RelationshipType ID="WorkItemGroup.3a962c1115fc4c9782510df178aae29c_Contains_System.WorkItem.ServiceRequest" Accessibility="Public" Abstract="false" Base="System_WorkItem_Library!System.WorkItemGroupContainsWorkItems">
          <Source ID="ContainedByGroup" MinCardinality="0" MaxCardinality="2147483647" Type="WorkItemGroup.3a962c1115fc4c9782510df178aae29c" />
          <Target ID="GroupContains" MinCardinality="0" MaxCardinality="2147483647" Type="System_WorkItem_ServiceRequest_Library!System.WorkItem.ServiceRequest" />
        </RelationshipType>
      </RelationshipTypes>
      <EnumerationTypes>
        <EnumerationValue ID="TestGroup106_Enum" Accessibility="Public" Parent="System_WorkItem_Incident_Library!IncidentTierQueuesEnum" Ordinal="106" />
      </EnumerationTypes>
    </EntityTypes>
  </TypeDefinitions>
  <Categories>
    <Category ID="Category.b18cbf4799bb43358c7f49770a1e030d" Target="NotificationSubscription821765ea45df49f282165a0ebba46db7" Value="EnterpriseManagement!Microsoft.EnterpriseManagement.ServiceManager.Rules.WorkflowSubscriptions" />
    <Category ID="Category.2d0a05daf1b74a638ada36f33e62d505" Target="NotificationSubscription041ee7779b87404794f2e1f653b3e69c" Value="EnterpriseManagement!Microsoft.EnterpriseManagement.ServiceManager.Rules.WorkflowSubscriptions" />
    <Category ID="Category.3d65406eb5ac48cfa8d181126726c8f5" Target="NotificationSubscriptioneccb3046f23340ecb29d0e4e750ae44a" Value="EnterpriseManagement!Microsoft.EnterpriseManagement.ServiceManager.Rules.WorkflowSubscriptions" />
    <Category ID="Category.d0c8e62605c84eb9b2e5c3c3b0731eeb" Target="NotificationSubscription487149f2df2b4b80a624ef7229fdc906" Value="EnterpriseManagement!Microsoft.EnterpriseManagement.ServiceManager.Rules.WorkflowSubscriptions" />
    <Category ID="Category.0215c9a9d429411eaed94175b14deb58" Target="NotificationSubscription1fc97793aaae434789ab2d6c1bec0ee1" Value="EnterpriseManagement!Microsoft.EnterpriseManagement.ServiceManager.Rules.WorkflowSubscriptions" />
    <Category ID="Category.3e0b0cabc6f24bfab520cd48e3d69cce" Target="NotificationSubscriptionb6d7290024bb4a31a2aa6efbb708b3c0" Value="EnterpriseManagement!Microsoft.EnterpriseManagement.ServiceManager.Rules.WorkflowSubscriptions" />
    <Category ID="Category.061c69c8ec1c4d3fbf9fbbff81b8a6fc" Target="NotificationSubscription680c4416df1741589d5883953e329ad0" Value="EnterpriseManagement!Microsoft.EnterpriseManagement.ServiceManager.Rules.WorkflowSubscriptions" />
    <Category ID="Category.05677c4842ef483c985a45a552315b63" Target="NotificationSubscriptiona11752eb53c44e068e922804724fff19" Value="EnterpriseManagement!Microsoft.EnterpriseManagement.ServiceManager.Rules.WorkflowSubscriptions" />
    <Category ID="Category.9051acd16bac4fccb1fa7cb26a36725f" Target="NotificationSubscription3ef721c864de4e43aada0ae05786bb89" Value="EnterpriseManagement!Microsoft.EnterpriseManagement.ServiceManager.Rules.WorkflowSubscriptions" />
    <Category ID="Category.275d58fd4c4f4de29082879e6803dd61" Target="NotificationSubscriptione4e7c2674e4d426fb5ee0a7ede1235a2" Value="EnterpriseManagement!Microsoft.EnterpriseManagement.ServiceManager.Rules.WorkflowSubscriptions" />
    <Category ID="Category.0c642d66d74c4efe8ec1a58068608167" Target="NotificationSubscription9b34e792a306416099259783ef6febe0" Value="EnterpriseManagement!Microsoft.EnterpriseManagement.ServiceManager.Rules.WorkflowSubscriptions" />
    <Category ID="Category.4ad772c646bd470dab2298a5e8ae16f9" Target="NotificationSubscription2226ce77949a44f8a83382b5e66defa0" Value="EnterpriseManagement!Microsoft.EnterpriseManagement.ServiceManager.Rules.WorkflowSubscriptions" />
    <Category ID="Category.cefa3ecb98cc4bc6b5f6f5c0388bd38d" Target="NotificationSubscription55e3a8bf3d75447989c79541aeef8ba9" Value="EnterpriseManagement!Microsoft.EnterpriseManagement.ServiceManager.Rules.WorkflowSubscriptions" />
    <Category ID="Category.1d1c2352bfba442d8802bc40197c4830" Target="NotificationSubscription0d5244f925c441c7ba20965e7f3ca63e" Value="EnterpriseManagement!Microsoft.EnterpriseManagement.ServiceManager.Rules.WorkflowSubscriptions" />
  </Categories>
  <Monitoring>
    <Discoveries>
      <Discovery ID="WorkItemGroup.e690c6be0f524fc48de129b80982f39d.Discovery" Enabled="true" Target="WorkItemGroup.e690c6be0f524fc48de129b80982f39d" ConfirmDelivery="false" Remotable="true" Priority="Normal">
        <Category>Discovery</Category>
        <DiscoveryTypes>
          <DiscoveryRelationship TypeID="WorkItemGroup.e690c6be0f524fc48de129b80982f39d_Contains_System.WorkItem.Incident" />
        </DiscoveryTypes>
        <DataSource ID="GroupPopulationDataSource" TypeID="Microsoft_SystemCenter_Library!Microsoft.SystemCenter.GroupPopulator">
          <RuleId>$MPElement$</RuleId>
          <GroupInstanceId>$MPElement[Name="WorkItemGroup.e690c6be0f524fc48de129b80982f39d"]$</GroupInstanceId>
          <MembershipRules>
            <MembershipRule>
              <MonitoringClass>$MPElement[Name="System_WorkItem_Incident_Library!System.WorkItem.Incident"]$</MonitoringClass>
              <RelationshipClass>$MPElement[Name="WorkItemGroup.e690c6be0f524fc48de129b80982f39d_Contains_System.WorkItem.Incident"]$</RelationshipClass>
              <Expression>
                <SimpleExpression>
                  <ValueExpression>
                    <Property>$Context/Property[Type='System_WorkItem_Incident_Library!System.WorkItem.Incident']/TierQueue$</Property>
                  </ValueExpression>
                  <Operator>Equal</Operator>
                  <ValueExpression>
                    <Value>{cff2195c-cb6f-38f9-305d-a2f6b4da2956}</Value>
                  </ValueExpression>
                </SimpleExpression>
              </Expression>
            </MembershipRule>
          </MembershipRules>
        </DataSource>
      </Discovery>
      <Discovery ID="WorkItemGroup.43216343a63c404f8be26c0f59cbee03.Discovery" Enabled="true" Target="WorkItemGroup.43216343a63c404f8be26c0f59cbee03" ConfirmDelivery="false" Remotable="true" Priority="Normal">
        <Category>Discovery</Category>
        <DiscoveryTypes>
          <DiscoveryRelationship TypeID="WorkItemGroup.43216343a63c404f8be26c0f59cbee03_Contains_System.WorkItem.ChangeRequest" />
        </DiscoveryTypes>
        <DataSource ID="GroupPopulationDataSource" TypeID="Microsoft_SystemCenter_Library!Microsoft.SystemCenter.GroupPopulator">
          <RuleId>$MPElement$</RuleId>
          <GroupInstanceId>$MPElement[Name="WorkItemGroup.43216343a63c404f8be26c0f59cbee03"]$</GroupInstanceId>
          <MembershipRules>
            <MembershipRule>
              <MonitoringClass>$MPElement[Name="System_WorkItem_ChangeRequest_Library!System.WorkItem.ChangeRequest"]$</MonitoringClass>
              <RelationshipClass>$MPElement[Name="WorkItemGroup.43216343a63c404f8be26c0f59cbee03_Contains_System.WorkItem.ChangeRequest"]$</RelationshipClass>
              <Expression>
                <SimpleExpression>
                  <ValueExpression>
                    <Property>$Context/Property[Type='System_WorkItem_ChangeRequest_Library!System.WorkItem.ChangeRequest']/TierQueue$</Property>
                  </ValueExpression>
                  <Operator>Equal</Operator>
                  <ValueExpression>
                    <Value>{cff2195c-cb6f-38f9-305d-a2f6b4da2956}</Value>
                  </ValueExpression>
                </SimpleExpression>
              </Expression>
            </MembershipRule>
          </MembershipRules>
        </DataSource>
      </Discovery>
      <Discovery ID="WorkItemGroup.7245d0f8a5984b5bb557f7cc1baac603.Discovery" Enabled="true" Target="WorkItemGroup.7245d0f8a5984b5bb557f7cc1baac603" ConfirmDelivery="false" Remotable="true" Priority="Normal">
        <Category>Discovery</Category>
        <DiscoveryTypes>
          <DiscoveryRelationship TypeID="WorkItemGroup.7245d0f8a5984b5bb557f7cc1baac603_Contains_System.WorkItem.Problem" />
        </DiscoveryTypes>
        <DataSource ID="GroupPopulationDataSource" TypeID="Microsoft_SystemCenter_Library!Microsoft.SystemCenter.GroupPopulator">
          <RuleId>$MPElement$</RuleId>
          <GroupInstanceId>$MPElement[Name="WorkItemGroup.7245d0f8a5984b5bb557f7cc1baac603"]$</GroupInstanceId>
          <MembershipRules>
            <MembershipRule>
              <MonitoringClass>$MPElement[Name="System_WorkItem_Problem_Library!System.WorkItem.Problem"]$</MonitoringClass>
              <RelationshipClass>$MPElement[Name="WorkItemGroup.7245d0f8a5984b5bb557f7cc1baac603_Contains_System.WorkItem.Problem"]$</RelationshipClass>
              <Expression>
                <SimpleExpression>
                  <ValueExpression>
                    <Property>$Context/Property[Type='System_WorkItem_Problem_Library!System.WorkItem.Problem']/TierQueue$</Property>
                  </ValueExpression>
                  <Operator>Equal</Operator>
                  <ValueExpression>
                    <Value>{cff2195c-cb6f-38f9-305d-a2f6b4da2956}</Value>
                  </ValueExpression>
                </SimpleExpression>
              </Expression>
            </MembershipRule>
          </MembershipRules>
        </DataSource>
      </Discovery>
      <Discovery ID="WorkItemGroup.3a962c1115fc4c9782510df178aae29c.Discovery" Enabled="true" Target="WorkItemGroup.3a962c1115fc4c9782510df178aae29c" ConfirmDelivery="false" Remotable="true" Priority="Normal">
        <Category>Discovery</Category>
        <DiscoveryTypes>
          <DiscoveryRelationship TypeID="WorkItemGroup.3a962c1115fc4c9782510df178aae29c_Contains_System.WorkItem.ServiceRequest" />
        </DiscoveryTypes>
        <DataSource ID="GroupPopulationDataSource" TypeID="Microsoft_SystemCenter_Library!Microsoft.SystemCenter.GroupPopulator">
          <RuleId>$MPElement$</RuleId>
          <GroupInstanceId>$MPElement[Name="WorkItemGroup.3a962c1115fc4c9782510df178aae29c"]$</GroupInstanceId>
          <MembershipRules>
            <MembershipRule>
              <MonitoringClass>$MPElement[Name="System_WorkItem_ServiceRequest_Library!System.WorkItem.ServiceRequest"]$</MonitoringClass>
              <RelationshipClass>$MPElement[Name="WorkItemGroup.3a962c1115fc4c9782510df178aae29c_Contains_System.WorkItem.ServiceRequest"]$</RelationshipClass>
              <Expression>
                <SimpleExpression>
                  <ValueExpression>
                    <Property>$Context/Property[Type='System_WorkItem_ServiceRequest_Library!System.WorkItem.ServiceRequest']/TierQueue$</Property>
                  </ValueExpression>
                  <Operator>Equal</Operator>
                  <ValueExpression>
                    <Value>{cff2195c-cb6f-38f9-305d-a2f6b4da2956}</Value>
                  </ValueExpression>
                </SimpleExpression>
              </Expression>
            </MembershipRule>
          </MembershipRules>
        </DataSource>
      </Discovery>
    </Discoveries>
    <Rules>
      <Rule ID="NotificationSubscription821765ea45df49f282165a0ebba46db7" Enabled="true" Target="Microsoft_SystemCenter_Library!Microsoft.SystemCenter.SubscriptionWorkflowTarget" ConfirmDelivery="true" Remotable="true" Priority="Normal" DiscardLevel="100">
        <Category>System</Category>
        <DataSources>
          <DataSource ID="DS" TypeID="SystemCenter!Microsoft.SystemCenter.CmdbInstanceSubscription.DataSourceModule">
            <Subscription>
              <InstanceSubscription Type="a604b942-4c7b-2fb2-28dc-61dc6f465c68">
                <AddInstance>
                  <Criteria>
                    <Expression>
                      <SimpleExpression>
                        <ValueExpression>
                          <Property State="Post">$Context/Property[Type='System_WorkItem_Incident_Library!System.WorkItem.Incident']/TierQueue$</Property>
                        </ValueExpression>
                        <Operator>Equal</Operator>
                        <ValueExpression>
                          <Value>{cff2195c-cb6f-38f9-305d-a2f6b4da2956}</Value>
                        </ValueExpression>
                      </SimpleExpression>
                    </Expression>
                  </Criteria>
                </AddInstance>
              </InstanceSubscription>
              <PollingIntervalInSeconds>60</PollingIntervalInSeconds>
              <BatchSize>100</BatchSize>
            </Subscription>
          </DataSource>
        </DataSources>
        <WriteActions>
          <WriteAction ID="WA" TypeID="SystemCenter!Microsoft.EnterpriseManagement.SystemCenter.Subscription.WindowsWorkflowTaskWriteAction">
            <Subscription>
              <VisibleWorkflowStatusUi>true</VisibleWorkflowStatusUi>
              <EnableBatchProcessing>false</EnableBatchProcessing>
              <WindowsWorkflowConfiguration>
                <AssemblyName>Microsoft.EnterpriseManagement.Notifications.Workflows</AssemblyName>
                <WorkflowTypeName>Microsoft.EnterpriseManagement.Notifications.Workflows.SendNotificationsActivity</WorkflowTypeName>
                <WorkflowParameters>
                  <WorkflowParameter Name="SubscriptionId" Type="guid">$MPElement$</WorkflowParameter>
                  <WorkflowParameter Name="DataItem" Type="string">$Data/.$</WorkflowParameter>
                  <WorkflowParameter Name="InstanceId" Type="string">$Data/BaseManagedEntityId$</WorkflowParameter>
                  <WorkflowArrayParameter Name="TemplateIds" Type="string">
                    <Item>5d822e13-666e-d8f6-dd81-ed898a6001ed</Item>
                  </WorkflowArrayParameter>
                  <WorkflowArrayParameter Name="PrimaryUserList" Type="string">
                    <Item>5fb06705-61ca-dc2e-457e-cfdb323daf53</Item>
                  </WorkflowArrayParameter>
                </WorkflowParameters>
                <RetryExceptions />
                <RetryDelaySeconds>60</RetryDelaySeconds>
                <MaximumRunningTimeSeconds>7200</MaximumRunningTimeSeconds>
              </WindowsWorkflowConfiguration>
            </Subscription>
          </WriteAction>
        </WriteActions>
      </Rule>
      <Rule ID="NotificationSubscription041ee7779b87404794f2e1f653b3e69c" Enabled="true" Target="Microsoft_SystemCenter_Library!Microsoft.SystemCenter.SubscriptionWorkflowTarget" ConfirmDelivery="true" Remotable="true" Priority="Normal" DiscardLevel="100">
        <Category>System</Category>
        <DataSources>
          <DataSource ID="DS" TypeID="SystemCenter!Microsoft.SystemCenter.CmdbInstanceSubscription.DataSourceModule">
            <Subscription>
              <InstanceSubscription Type="a604b942-4c7b-2fb2-28dc-61dc6f465c68">
                <UpdateInstance>
                  <Criteria>
                    <Expression>
                      <SimpleExpression>
                        <ValueExpression>
                          <Property State="Post">$Context/Property[Type='System_WorkItem_Incident_Library!System.WorkItem.Incident']/TierQueue$</Property>
                        </ValueExpression>
                        <Operator>Equal</Operator>
                        <ValueExpression>
                          <Value>{cff2195c-cb6f-38f9-305d-a2f6b4da2956}</Value>
                        </ValueExpression>
                      </SimpleExpression>
                    </Expression>
                  </Criteria>
                </UpdateInstance>
              </InstanceSubscription>
              <PollingIntervalInSeconds>60</PollingIntervalInSeconds>
              <BatchSize>100</BatchSize>
            </Subscription>
          </DataSource>
        </DataSources>
        <WriteActions>
          <WriteAction ID="WA" TypeID="SystemCenter!Microsoft.EnterpriseManagement.SystemCenter.Subscription.WindowsWorkflowTaskWriteAction">
            <Subscription>
              <VisibleWorkflowStatusUi>true</VisibleWorkflowStatusUi>
              <EnableBatchProcessing>false</EnableBatchProcessing>
              <WindowsWorkflowConfiguration>
                <AssemblyName>Microsoft.EnterpriseManagement.Notifications.Workflows</AssemblyName>
                <WorkflowTypeName>Microsoft.EnterpriseManagement.Notifications.Workflows.SendNotificationsActivity</WorkflowTypeName>
                <WorkflowParameters>
                  <WorkflowParameter Name="SubscriptionId" Type="guid">$MPElement$</WorkflowParameter>
                  <WorkflowParameter Name="DataItem" Type="string">$Data/.$</WorkflowParameter>
                  <WorkflowParameter Name="InstanceId" Type="string">$Data/BaseManagedEntityId$</WorkflowParameter>
                  <WorkflowArrayParameter Name="TemplateIds" Type="string">
                    <Item>5d822e13-666e-d8f6-dd81-ed898a6001ed</Item>
                  </WorkflowArrayParameter>
                  <WorkflowArrayParameter Name="PrimaryUserList" Type="string">
                    <Item>5fb06705-61ca-dc2e-457e-cfdb323daf53</Item>
                  </WorkflowArrayParameter>
                </WorkflowParameters>
                <RetryExceptions />
                <RetryDelaySeconds>60</RetryDelaySeconds>
                <MaximumRunningTimeSeconds>7200</MaximumRunningTimeSeconds>
              </WindowsWorkflowConfiguration>
            </Subscription>
          </WriteAction>
        </WriteActions>
      </Rule>
      <Rule ID="NotificationSubscriptioneccb3046f23340ecb29d0e4e750ae44a" Enabled="true" Target="Microsoft_SystemCenter_Library!Microsoft.SystemCenter.SubscriptionWorkflowTarget" ConfirmDelivery="true" Remotable="true" Priority="Normal" DiscardLevel="100">
        <Category>System</Category>
        <DataSources>
          <DataSource ID="DS" TypeID="SystemCenter!Microsoft.SystemCenter.CmdbInstanceSubscription.DataSourceModule">
            <Subscription>
              <InstanceSubscription Type="e6c9cf6e-d7fe-1b5d-216c-c3f5d2c7670c">
                <AddInstance>
                  <Criteria>
                    <Expression>
                      <SimpleExpression>
                        <ValueExpression>
                          <Property State="Post">$Context/Property[Type='System_WorkItem_ChangeRequest_Library!System.WorkItem.ChangeRequest']/TierQueue$</Property>
                        </ValueExpression>
                        <Operator>Equal</Operator>
                        <ValueExpression>
                          <Value>{cff2195c-cb6f-38f9-305d-a2f6b4da2956}</Value>
                        </ValueExpression>
                      </SimpleExpression>
                    </Expression>
                  </Criteria>
                </AddInstance>
              </InstanceSubscription>
              <PollingIntervalInSeconds>60</PollingIntervalInSeconds>
              <BatchSize>100</BatchSize>
            </Subscription>
          </DataSource>
        </DataSources>
        <WriteActions>
          <WriteAction ID="WA" TypeID="SystemCenter!Microsoft.EnterpriseManagement.SystemCenter.Subscription.WindowsWorkflowTaskWriteAction">
            <Subscription>
              <VisibleWorkflowStatusUi>true</VisibleWorkflowStatusUi>
              <EnableBatchProcessing>false</EnableBatchProcessing>
              <WindowsWorkflowConfiguration>
                <AssemblyName>Microsoft.EnterpriseManagement.Notifications.Workflows</AssemblyName>
                <WorkflowTypeName>Microsoft.EnterpriseManagement.Notifications.Workflows.SendNotificationsActivity</WorkflowTypeName>
                <WorkflowParameters>
                  <WorkflowParameter Name="SubscriptionId" Type="guid">$MPElement$</WorkflowParameter>
                  <WorkflowParameter Name="DataItem" Type="string">$Data/.$</WorkflowParameter>
                  <WorkflowParameter Name="InstanceId" Type="string">$Data/BaseManagedEntityId$</WorkflowParameter>
                  <WorkflowArrayParameter Name="TemplateIds" Type="string">
                    <Item>a733e5da-1591-dcfc-2111-7b2a8da9070f</Item>
                  </WorkflowArrayParameter>
                  <WorkflowArrayParameter Name="PrimaryUserList" Type="string">
                    <Item>5fb06705-61ca-dc2e-457e-cfdb323daf53</Item>
                  </WorkflowArrayParameter>
                </WorkflowParameters>
                <RetryExceptions />
                <RetryDelaySeconds>60</RetryDelaySeconds>
                <MaximumRunningTimeSeconds>7200</MaximumRunningTimeSeconds>
              </WindowsWorkflowConfiguration>
            </Subscription>
          </WriteAction>
        </WriteActions>
      </Rule>
      <Rule ID="NotificationSubscription487149f2df2b4b80a624ef7229fdc906" Enabled="true" Target="Microsoft_SystemCenter_Library!Microsoft.SystemCenter.SubscriptionWorkflowTarget" ConfirmDelivery="true" Remotable="true" Priority="Normal" DiscardLevel="100">
        <Category>System</Category>
        <DataSources>
          <DataSource ID="DS" TypeID="SystemCenter!Microsoft.SystemCenter.CmdbInstanceSubscription.DataSourceModule">
            <Subscription>
              <InstanceSubscription Type="e6c9cf6e-d7fe-1b5d-216c-c3f5d2c7670c">
                <UpdateInstance>
                  <Criteria>
                    <Expression>
                      <SimpleExpression>
                        <ValueExpression>
                          <Property State="Post">$Context/Property[Type='System_WorkItem_ChangeRequest_Library!System.WorkItem.ChangeRequest']/TierQueue$</Property>
                        </ValueExpression>
                        <Operator>Equal</Operator>
                        <ValueExpression>
                          <Value>{cff2195c-cb6f-38f9-305d-a2f6b4da2956}</Value>
                        </ValueExpression>
                      </SimpleExpression>
                    </Expression>
                  </Criteria>
                </UpdateInstance>
              </InstanceSubscription>
              <PollingIntervalInSeconds>60</PollingIntervalInSeconds>
              <BatchSize>100</BatchSize>
            </Subscription>
          </DataSource>
        </DataSources>
        <WriteActions>
          <WriteAction ID="WA" TypeID="SystemCenter!Microsoft.EnterpriseManagement.SystemCenter.Subscription.WindowsWorkflowTaskWriteAction">
            <Subscription>
              <VisibleWorkflowStatusUi>true</VisibleWorkflowStatusUi>
              <EnableBatchProcessing>false</EnableBatchProcessing>
              <WindowsWorkflowConfiguration>
                <AssemblyName>Microsoft.EnterpriseManagement.Notifications.Workflows</AssemblyName>
                <WorkflowTypeName>Microsoft.EnterpriseManagement.Notifications.Workflows.SendNotificationsActivity</WorkflowTypeName>
                <WorkflowParameters>
                  <WorkflowParameter Name="SubscriptionId" Type="guid">$MPElement$</WorkflowParameter>
                  <WorkflowParameter Name="DataItem" Type="string">$Data/.$</WorkflowParameter>
                  <WorkflowParameter Name="InstanceId" Type="string">$Data/BaseManagedEntityId$</WorkflowParameter>
                  <WorkflowArrayParameter Name="TemplateIds" Type="string">
                    <Item>a733e5da-1591-dcfc-2111-7b2a8da9070f</Item>
                  </WorkflowArrayParameter>
                  <WorkflowArrayParameter Name="PrimaryUserList" Type="string">
                    <Item>5fb06705-61ca-dc2e-457e-cfdb323daf53</Item>
                  </WorkflowArrayParameter>
                </WorkflowParameters>
                <RetryExceptions />
                <RetryDelaySeconds>60</RetryDelaySeconds>
                <MaximumRunningTimeSeconds>7200</MaximumRunningTimeSeconds>
              </WindowsWorkflowConfiguration>
            </Subscription>
          </WriteAction>
        </WriteActions>
      </Rule>
      <Rule ID="NotificationSubscription1fc97793aaae434789ab2d6c1bec0ee1" Enabled="true" Target="Microsoft_SystemCenter_Library!Microsoft.SystemCenter.SubscriptionWorkflowTarget" ConfirmDelivery="true" Remotable="true" Priority="Normal" DiscardLevel="100">
        <Category>System</Category>
        <DataSources>
          <DataSource ID="DS" TypeID="SystemCenter!Microsoft.SystemCenter.CmdbInstanceSubscription.DataSourceModule">
            <Subscription>
              <InstanceSubscription Type="422afc88-5eff-f4c5-f8f6-e01038cde67f">
                <AddInstance>
                  <Criteria>
                    <Expression>
                      <SimpleExpression>
                        <ValueExpression>
                          <Property State="Post">$Context/Property[Type='System_WorkItem_Problem_Library!System.WorkItem.Problem']/TierQueue$</Property>
                        </ValueExpression>
                        <Operator>Equal</Operator>
                        <ValueExpression>
                          <Value>{cff2195c-cb6f-38f9-305d-a2f6b4da2956}</Value>
                        </ValueExpression>
                      </SimpleExpression>
                    </Expression>
                  </Criteria>
                </AddInstance>
              </InstanceSubscription>
              <PollingIntervalInSeconds>60</PollingIntervalInSeconds>
              <BatchSize>100</BatchSize>
            </Subscription>
          </DataSource>
        </DataSources>
        <WriteActions>
          <WriteAction ID="WA" TypeID="SystemCenter!Microsoft.EnterpriseManagement.SystemCenter.Subscription.WindowsWorkflowTaskWriteAction">
            <Subscription>
              <VisibleWorkflowStatusUi>true</VisibleWorkflowStatusUi>
              <EnableBatchProcessing>false</EnableBatchProcessing>
              <WindowsWorkflowConfiguration>
                <AssemblyName>Microsoft.EnterpriseManagement.Notifications.Workflows</AssemblyName>
                <WorkflowTypeName>Microsoft.EnterpriseManagement.Notifications.Workflows.SendNotificationsActivity</WorkflowTypeName>
                <WorkflowParameters>
                  <WorkflowParameter Name="SubscriptionId" Type="guid">$MPElement$</WorkflowParameter>
                  <WorkflowParameter Name="DataItem" Type="string">$Data/.$</WorkflowParameter>
                  <WorkflowParameter Name="InstanceId" Type="string">$Data/BaseManagedEntityId$</WorkflowParameter>
                  <WorkflowArrayParameter Name="TemplateIds" Type="string">
                    <Item>18bce03c-089d-8cf7-1214-309192443c77</Item>
                  </WorkflowArrayParameter>
                  <WorkflowArrayParameter Name="PrimaryUserList" Type="string">
                    <Item>5fb06705-61ca-dc2e-457e-cfdb323daf53</Item>
                  </WorkflowArrayParameter>
                </WorkflowParameters>
                <RetryExceptions />
                <RetryDelaySeconds>60</RetryDelaySeconds>
                <MaximumRunningTimeSeconds>7200</MaximumRunningTimeSeconds>
              </WindowsWorkflowConfiguration>
            </Subscription>
          </WriteAction>
        </WriteActions>
      </Rule>
      <Rule ID="NotificationSubscriptionb6d7290024bb4a31a2aa6efbb708b3c0" Enabled="true" Target="Microsoft_SystemCenter_Library!Microsoft.SystemCenter.SubscriptionWorkflowTarget" ConfirmDelivery="true" Remotable="true" Priority="Normal" DiscardLevel="100">
        <Category>System</Category>
        <DataSources>
          <DataSource ID="DS" TypeID="SystemCenter!Microsoft.SystemCenter.CmdbInstanceSubscription.DataSourceModule">
            <Subscription>
              <InstanceSubscription Type="422afc88-5eff-f4c5-f8f6-e01038cde67f">
                <UpdateInstance>
                  <Criteria>
                    <Expression>
                      <SimpleExpression>
                        <ValueExpression>
                          <Property State="Post">$Context/Property[Type='System_WorkItem_Problem_Library!System.WorkItem.Problem']/TierQueue$</Property>
                        </ValueExpression>
                        <Operator>Equal</Operator>
                        <ValueExpression>
                          <Value>{cff2195c-cb6f-38f9-305d-a2f6b4da2956}</Value>
                        </ValueExpression>
                      </SimpleExpression>
                    </Expression>
                  </Criteria>
                </UpdateInstance>
              </InstanceSubscription>
              <PollingIntervalInSeconds>60</PollingIntervalInSeconds>
              <BatchSize>100</BatchSize>
            </Subscription>
          </DataSource>
        </DataSources>
        <WriteActions>
          <WriteAction ID="WA" TypeID="SystemCenter!Microsoft.EnterpriseManagement.SystemCenter.Subscription.WindowsWorkflowTaskWriteAction">
            <Subscription>
              <VisibleWorkflowStatusUi>true</VisibleWorkflowStatusUi>
              <EnableBatchProcessing>false</EnableBatchProcessing>
              <WindowsWorkflowConfiguration>
                <AssemblyName>Microsoft.EnterpriseManagement.Notifications.Workflows</AssemblyName>
                <WorkflowTypeName>Microsoft.EnterpriseManagement.Notifications.Workflows.SendNotificationsActivity</WorkflowTypeName>
                <WorkflowParameters>
                  <WorkflowParameter Name="SubscriptionId" Type="guid">$MPElement$</WorkflowParameter>
                  <WorkflowParameter Name="DataItem" Type="string">$Data/.$</WorkflowParameter>
                  <WorkflowParameter Name="InstanceId" Type="string">$Data/BaseManagedEntityId$</WorkflowParameter>
                  <WorkflowArrayParameter Name="TemplateIds" Type="string">
                    <Item>18bce03c-089d-8cf7-1214-309192443c77</Item>
                  </WorkflowArrayParameter>
                  <WorkflowArrayParameter Name="PrimaryUserList" Type="string">
                    <Item>5fb06705-61ca-dc2e-457e-cfdb323daf53</Item>
                  </WorkflowArrayParameter>
                </WorkflowParameters>
                <RetryExceptions />
                <RetryDelaySeconds>60</RetryDelaySeconds>
                <MaximumRunningTimeSeconds>7200</MaximumRunningTimeSeconds>
              </WindowsWorkflowConfiguration>
            </Subscription>
          </WriteAction>
        </WriteActions>
      </Rule>
      <Rule ID="NotificationSubscription680c4416df1741589d5883953e329ad0" Enabled="true" Target="Microsoft_SystemCenter_Library!Microsoft.SystemCenter.SubscriptionWorkflowTarget" ConfirmDelivery="true" Remotable="true" Priority="Normal" DiscardLevel="100">
        <Category>System</Category>
        <DataSources>
          <DataSource ID="DS" TypeID="SystemCenter!Microsoft.SystemCenter.CmdbInstanceSubscription.DataSourceModule">
            <Subscription>
              <InstanceSubscription Type="04b69835-6343-4de2-4b19-6be08c612989">
                <AddInstance>
                  <Criteria>
                    <Expression>
                      <SimpleExpression>
                        <ValueExpression>
                          <Property State="Post">$Context/Property[Type='System_WorkItem_ServiceRequest_Library!System.WorkItem.ServiceRequest']/TierQueue$</Property>
                        </ValueExpression>
                        <Operator>Equal</Operator>
                        <ValueExpression>
                          <Value>{cff2195c-cb6f-38f9-305d-a2f6b4da2956}</Value>
                        </ValueExpression>
                      </SimpleExpression>
                    </Expression>
                  </Criteria>
                </AddInstance>
              </InstanceSubscription>
              <PollingIntervalInSeconds>60</PollingIntervalInSeconds>
              <BatchSize>100</BatchSize>
            </Subscription>
          </DataSource>
        </DataSources>
        <WriteActions>
          <WriteAction ID="WA" TypeID="SystemCenter!Microsoft.EnterpriseManagement.SystemCenter.Subscription.WindowsWorkflowTaskWriteAction">
            <Subscription>
              <VisibleWorkflowStatusUi>true</VisibleWorkflowStatusUi>
              <EnableBatchProcessing>false</EnableBatchProcessing>
              <WindowsWorkflowConfiguration>
                <AssemblyName>Microsoft.EnterpriseManagement.Notifications.Workflows</AssemblyName>
                <WorkflowTypeName>Microsoft.EnterpriseManagement.Notifications.Workflows.SendNotificationsActivity</WorkflowTypeName>
                <WorkflowParameters>
                  <WorkflowParameter Name="SubscriptionId" Type="guid">$MPElement$</WorkflowParameter>
                  <WorkflowParameter Name="DataItem" Type="string">$Data/.$</WorkflowParameter>
                  <WorkflowParameter Name="InstanceId" Type="string">$Data/BaseManagedEntityId$</WorkflowParameter>
                  <WorkflowArrayParameter Name="TemplateIds" Type="string">
                    <Item>6f7884a4-4eed-dc3b-315a-d039cbace3ad</Item>
                  </WorkflowArrayParameter>
                  <WorkflowArrayParameter Name="PrimaryUserList" Type="string">
                    <Item>5fb06705-61ca-dc2e-457e-cfdb323daf53</Item>
                  </WorkflowArrayParameter>
                </WorkflowParameters>
                <RetryExceptions />
                <RetryDelaySeconds>60</RetryDelaySeconds>
                <MaximumRunningTimeSeconds>7200</MaximumRunningTimeSeconds>
              </WindowsWorkflowConfiguration>
            </Subscription>
          </WriteAction>
        </WriteActions>
      </Rule>
      <Rule ID="NotificationSubscriptiona11752eb53c44e068e922804724fff19" Enabled="true" Target="Microsoft_SystemCenter_Library!Microsoft.SystemCenter.SubscriptionWorkflowTarget" ConfirmDelivery="true" Remotable="true" Priority="Normal" DiscardLevel="100">
        <Category>System</Category>
        <DataSources>
          <DataSource ID="DS" TypeID="SystemCenter!Microsoft.SystemCenter.CmdbInstanceSubscription.DataSourceModule">
            <Subscription>
              <InstanceSubscription Type="04b69835-6343-4de2-4b19-6be08c612989">
                <UpdateInstance>
                  <Criteria>
                    <Expression>
                      <SimpleExpression>
                        <ValueExpression>
                          <Property State="Post">$Context/Property[Type='System_WorkItem_ServiceRequest_Library!System.WorkItem.ServiceRequest']/TierQueue$</Property>
                        </ValueExpression>
                        <Operator>Equal</Operator>
                        <ValueExpression>
                          <Value>{cff2195c-cb6f-38f9-305d-a2f6b4da2956}</Value>
                        </ValueExpression>
                      </SimpleExpression>
                    </Expression>
                  </Criteria>
                </UpdateInstance>
              </InstanceSubscription>
              <PollingIntervalInSeconds>60</PollingIntervalInSeconds>
              <BatchSize>100</BatchSize>
            </Subscription>
          </DataSource>
        </DataSources>
        <WriteActions>
          <WriteAction ID="WA" TypeID="SystemCenter!Microsoft.EnterpriseManagement.SystemCenter.Subscription.WindowsWorkflowTaskWriteAction">
            <Subscription>
              <VisibleWorkflowStatusUi>true</VisibleWorkflowStatusUi>
              <EnableBatchProcessing>false</EnableBatchProcessing>
              <WindowsWorkflowConfiguration>
                <AssemblyName>Microsoft.EnterpriseManagement.Notifications.Workflows</AssemblyName>
                <WorkflowTypeName>Microsoft.EnterpriseManagement.Notifications.Workflows.SendNotificationsActivity</WorkflowTypeName>
                <WorkflowParameters>
                  <WorkflowParameter Name="SubscriptionId" Type="guid">$MPElement$</WorkflowParameter>
                  <WorkflowParameter Name="DataItem" Type="string">$Data/.$</WorkflowParameter>
                  <WorkflowParameter Name="InstanceId" Type="string">$Data/BaseManagedEntityId$</WorkflowParameter>
                  <WorkflowArrayParameter Name="TemplateIds" Type="string">
                    <Item>6f7884a4-4eed-dc3b-315a-d039cbace3ad</Item>
                  </WorkflowArrayParameter>
                  <WorkflowArrayParameter Name="PrimaryUserList" Type="string">
                    <Item>5fb06705-61ca-dc2e-457e-cfdb323daf53</Item>
                  </WorkflowArrayParameter>
                </WorkflowParameters>
                <RetryExceptions />
                <RetryDelaySeconds>60</RetryDelaySeconds>
                <MaximumRunningTimeSeconds>7200</MaximumRunningTimeSeconds>
              </WindowsWorkflowConfiguration>
            </Subscription>
          </WriteAction>
        </WriteActions>
      </Rule>
      <Rule ID="NotificationSubscription3ef721c864de4e43aada0ae05786bb89" Enabled="true" Target="Microsoft_SystemCenter_Library!Microsoft.SystemCenter.SubscriptionWorkflowTarget" ConfirmDelivery="true" Remotable="true" Priority="Normal" DiscardLevel="100">
        <Category>System</Category>
        <DataSources>
          <DataSource ID="DS" TypeID="SystemCenter!Microsoft.SystemCenter.CmdbInstanceSubscription.DataSourceModule">
            <Subscription>
              <InstanceSubscription Type="04b69835-6343-4de2-4b19-6be08c612989">
                <UpdateInstance>
                  <Criteria>
                    <Expression>
                      <SimpleExpression>
                        <ValueExpression>
                          <Property State="Post">$Context/Property[Type='System_WorkItem_ServiceRequest_Library!System.WorkItem.ServiceRequest']/Status$</Property>
                        </ValueExpression>
                        <Operator>Equal</Operator>
                        <ValueExpression>
                          <Value>{b026fdfd-89bd-490b-e1fd-a599c78d440f}</Value>
                        </ValueExpression>
                      </SimpleExpression>
                    </Expression>
                  </Criteria>
                </UpdateInstance>
              </InstanceSubscription>
              <PollingIntervalInSeconds>60</PollingIntervalInSeconds>
              <BatchSize>100</BatchSize>
            </Subscription>
          </DataSource>
        </DataSources>
        <WriteActions>
          <WriteAction ID="WA" TypeID="SystemCenter!Microsoft.EnterpriseManagement.SystemCenter.Subscription.WindowsWorkflowTaskWriteAction">
            <Subscription>
              <VisibleWorkflowStatusUi>true</VisibleWorkflowStatusUi>
              <EnableBatchProcessing>false</EnableBatchProcessing>
              <WindowsWorkflowConfiguration>
                <AssemblyName>Microsoft.EnterpriseManagement.Notifications.Workflows</AssemblyName>
                <WorkflowTypeName>Microsoft.EnterpriseManagement.Notifications.Workflows.SendNotificationsActivity</WorkflowTypeName>
                <WorkflowParameters>
                  <WorkflowParameter Name="SubscriptionId" Type="guid">$MPElement$</WorkflowParameter>
                  <WorkflowParameter Name="DataItem" Type="string">$Data/.$</WorkflowParameter>
                  <WorkflowParameter Name="InstanceId" Type="string">$Data/BaseManagedEntityId$</WorkflowParameter>
                  <WorkflowArrayParameter Name="TemplateIds" Type="string">
                    <Item>6f7884a4-4eed-dc3b-315a-d039cbace3ad</Item>
                  </WorkflowArrayParameter>
                  <WorkflowArrayParameter Name="PrimaryUserList" Type="string">
                    <Item>5fb06705-61ca-dc2e-457e-cfdb323daf53</Item>
                  </WorkflowArrayParameter>
                </WorkflowParameters>
                <RetryExceptions />
                <RetryDelaySeconds>60</RetryDelaySeconds>
                <MaximumRunningTimeSeconds>7200</MaximumRunningTimeSeconds>
              </WindowsWorkflowConfiguration>
            </Subscription>
          </WriteAction>
        </WriteActions>
      </Rule>
      <Rule ID="NotificationSubscriptione4e7c2674e4d426fb5ee0a7ede1235a2" Enabled="true" Target="Microsoft_SystemCenter_Library!Microsoft.SystemCenter.SubscriptionWorkflowTarget" ConfirmDelivery="true" Remotable="true" Priority="Normal" DiscardLevel="100">
        <Category>System</Category>
        <DataSources>
          <DataSource ID="DS" TypeID="SystemCenter!Microsoft.SystemCenter.CmdbInstanceSubscription.DataSourceModule">
            <Subscription>
              <InstanceSubscription Type="04b69835-6343-4de2-4b19-6be08c612989">
                <UpdateInstance>
                  <Criteria>
                    <Expression>
                      <SimpleExpression>
                        <ValueExpression>
                          <Property State="Post">$Context/Property[Type='System_WorkItem_ServiceRequest_Library!System.WorkItem.ServiceRequest']/Status$</Property>
                        </ValueExpression>
                        <Operator>Equal</Operator>
                        <ValueExpression>
                          <Value>{c7b65747-f99e-c108-1e17-3c1062138fc4}</Value>
                        </ValueExpression>
                      </SimpleExpression>
                    </Expression>
                  </Criteria>
                </UpdateInstance>
              </InstanceSubscription>
              <PollingIntervalInSeconds>60</PollingIntervalInSeconds>
              <BatchSize>100</BatchSize>
            </Subscription>
          </DataSource>
        </DataSources>
        <WriteActions>
          <WriteAction ID="WA" TypeID="SystemCenter!Microsoft.EnterpriseManagement.SystemCenter.Subscription.WindowsWorkflowTaskWriteAction">
            <Subscription>
              <VisibleWorkflowStatusUi>true</VisibleWorkflowStatusUi>
              <EnableBatchProcessing>false</EnableBatchProcessing>
              <WindowsWorkflowConfiguration>
                <AssemblyName>Microsoft.EnterpriseManagement.Notifications.Workflows</AssemblyName>
                <WorkflowTypeName>Microsoft.EnterpriseManagement.Notifications.Workflows.SendNotificationsActivity</WorkflowTypeName>
                <WorkflowParameters>
                  <WorkflowParameter Name="SubscriptionId" Type="guid">$MPElement$</WorkflowParameter>
                  <WorkflowParameter Name="DataItem" Type="string">$Data/.$</WorkflowParameter>
                  <WorkflowParameter Name="InstanceId" Type="string">$Data/BaseManagedEntityId$</WorkflowParameter>
                  <WorkflowArrayParameter Name="TemplateIds" Type="string">
                    <Item>6f7884a4-4eed-dc3b-315a-d039cbace3ad</Item>
                  </WorkflowArrayParameter>
                  <WorkflowArrayParameter Name="PrimaryUserList" Type="string">
                    <Item>5fb06705-61ca-dc2e-457e-cfdb323daf53</Item>
                  </WorkflowArrayParameter>
                </WorkflowParameters>
                <RetryExceptions />
                <RetryDelaySeconds>60</RetryDelaySeconds>
                <MaximumRunningTimeSeconds>7200</MaximumRunningTimeSeconds>
              </WindowsWorkflowConfiguration>
            </Subscription>
          </WriteAction>
        </WriteActions>
      </Rule>
      <Rule ID="NotificationSubscription9b34e792a306416099259783ef6febe0" Enabled="true" Target="Microsoft_SystemCenter_Library!Microsoft.SystemCenter.SubscriptionWorkflowTarget" ConfirmDelivery="true" Remotable="true" Priority="Normal" DiscardLevel="100">
        <Category>System</Category>
        <DataSources>
          <DataSource ID="DS" TypeID="SystemCenter!Microsoft.SystemCenter.CmdbInstanceSubscription.DataSourceModule">
            <Subscription>
              <InstanceSubscription Type="e6c9cf6e-d7fe-1b5d-216c-c3f5d2c7670c">
                <UpdateInstance>
                  <Criteria>
                    <Expression>
                      <SimpleExpression>
                        <ValueExpression>
                          <Property State="Post">$Context/Property[Type='System_WorkItem_ChangeRequest_Library!System.WorkItem.ChangeRequest']/Status$</Property>
                        </ValueExpression>
                        <Operator>Equal</Operator>
                        <ValueExpression>
                          <Value>{68277330-a0d3-cfdd-298d-d5c31d1d126f}</Value>
                        </ValueExpression>
                      </SimpleExpression>
                    </Expression>
                  </Criteria>
                </UpdateInstance>
              </InstanceSubscription>
              <PollingIntervalInSeconds>60</PollingIntervalInSeconds>
              <BatchSize>100</BatchSize>
            </Subscription>
          </DataSource>
        </DataSources>
        <WriteActions>
          <WriteAction ID="WA" TypeID="SystemCenter!Microsoft.EnterpriseManagement.SystemCenter.Subscription.WindowsWorkflowTaskWriteAction">
            <Subscription>
              <VisibleWorkflowStatusUi>true</VisibleWorkflowStatusUi>
              <EnableBatchProcessing>false</EnableBatchProcessing>
              <WindowsWorkflowConfiguration>
                <AssemblyName>Microsoft.EnterpriseManagement.Notifications.Workflows</AssemblyName>
                <WorkflowTypeName>Microsoft.EnterpriseManagement.Notifications.Workflows.SendNotificationsActivity</WorkflowTypeName>
                <WorkflowParameters>
                  <WorkflowParameter Name="SubscriptionId" Type="guid">$MPElement$</WorkflowParameter>
                  <WorkflowParameter Name="DataItem" Type="string">$Data/.$</WorkflowParameter>
                  <WorkflowParameter Name="InstanceId" Type="string">$Data/BaseManagedEntityId$</WorkflowParameter>
                  <WorkflowArrayParameter Name="TemplateIds" Type="string">
                    <Item>a733e5da-1591-dcfc-2111-7b2a8da9070f</Item>
                  </WorkflowArrayParameter>
                  <WorkflowArrayParameter Name="PrimaryUserList" Type="string">
                    <Item>5fb06705-61ca-dc2e-457e-cfdb323daf53</Item>
                  </WorkflowArrayParameter>
                </WorkflowParameters>
                <RetryExceptions />
                <RetryDelaySeconds>60</RetryDelaySeconds>
                <MaximumRunningTimeSeconds>7200</MaximumRunningTimeSeconds>
              </WindowsWorkflowConfiguration>
            </Subscription>
          </WriteAction>
        </WriteActions>
      </Rule>
      <Rule ID="NotificationSubscription2226ce77949a44f8a83382b5e66defa0" Enabled="true" Target="Microsoft_SystemCenter_Library!Microsoft.SystemCenter.SubscriptionWorkflowTarget" ConfirmDelivery="true" Remotable="true" Priority="Normal" DiscardLevel="100">
        <Category>System</Category>
        <DataSources>
          <DataSource ID="DS" TypeID="SystemCenter!Microsoft.SystemCenter.CmdbInstanceSubscription.DataSourceModule">
            <Subscription>
              <InstanceSubscription Type="e6c9cf6e-d7fe-1b5d-216c-c3f5d2c7670c">
                <UpdateInstance>
                  <Criteria>
                    <Expression>
                      <SimpleExpression>
                        <ValueExpression>
                          <Property State="Post">$Context/Property[Type='System_WorkItem_ChangeRequest_Library!System.WorkItem.ChangeRequest']/Status$</Property>
                        </ValueExpression>
                        <Operator>Equal</Operator>
                        <ValueExpression>
                          <Value>{f228d50b-2b5a-010f-b1a4-5c7d95703a9b}</Value>
                        </ValueExpression>
                      </SimpleExpression>
                    </Expression>
                  </Criteria>
                </UpdateInstance>
              </InstanceSubscription>
              <PollingIntervalInSeconds>60</PollingIntervalInSeconds>
              <BatchSize>100</BatchSize>
            </Subscription>
          </DataSource>
        </DataSources>
        <WriteActions>
          <WriteAction ID="WA" TypeID="SystemCenter!Microsoft.EnterpriseManagement.SystemCenter.Subscription.WindowsWorkflowTaskWriteAction">
            <Subscription>
              <VisibleWorkflowStatusUi>true</VisibleWorkflowStatusUi>
              <EnableBatchProcessing>false</EnableBatchProcessing>
              <WindowsWorkflowConfiguration>
                <AssemblyName>Microsoft.EnterpriseManagement.Notifications.Workflows</AssemblyName>
                <WorkflowTypeName>Microsoft.EnterpriseManagement.Notifications.Workflows.SendNotificationsActivity</WorkflowTypeName>
                <WorkflowParameters>
                  <WorkflowParameter Name="SubscriptionId" Type="guid">$MPElement$</WorkflowParameter>
                  <WorkflowParameter Name="DataItem" Type="string">$Data/.$</WorkflowParameter>
                  <WorkflowParameter Name="InstanceId" Type="string">$Data/BaseManagedEntityId$</WorkflowParameter>
                  <WorkflowArrayParameter Name="TemplateIds" Type="string">
                    <Item>a733e5da-1591-dcfc-2111-7b2a8da9070f</Item>
                  </WorkflowArrayParameter>
                  <WorkflowArrayParameter Name="PrimaryUserList" Type="string">
                    <Item>5fb06705-61ca-dc2e-457e-cfdb323daf53</Item>
                  </WorkflowArrayParameter>
                </WorkflowParameters>
                <RetryExceptions />
                <RetryDelaySeconds>60</RetryDelaySeconds>
                <MaximumRunningTimeSeconds>7200</MaximumRunningTimeSeconds>
              </WindowsWorkflowConfiguration>
            </Subscription>
          </WriteAction>
        </WriteActions>
      </Rule>
      <Rule ID="NotificationSubscription55e3a8bf3d75447989c79541aeef8ba9" Enabled="true" Target="Microsoft_SystemCenter_Library!Microsoft.SystemCenter.SubscriptionWorkflowTarget" ConfirmDelivery="true" Remotable="true" Priority="Normal" DiscardLevel="100">
        <Category>System</Category>
        <DataSources>
          <DataSource ID="DS" TypeID="SystemCenter!Microsoft.SystemCenter.CmdbInstanceSubscription.DataSourceModule">
            <Subscription>
              <InstanceSubscription Type="a604b942-4c7b-2fb2-28dc-61dc6f465c68">
                <UpdateInstance>
                  <Criteria>
                    <Expression>
                      <SimpleExpression>
                        <ValueExpression>
                          <Property State="Post">$Context/Property[Type='System_WorkItem_Incident_Library!System.WorkItem.Incident']/Status$</Property>
                        </ValueExpression>
                        <Operator>Equal</Operator>
                        <ValueExpression>
                          <Value>{2b8830b6-59f0-f574-9c2a-f4b4682f1681}</Value>
                        </ValueExpression>
                      </SimpleExpression>
                    </Expression>
                  </Criteria>
                </UpdateInstance>
              </InstanceSubscription>
              <PollingIntervalInSeconds>60</PollingIntervalInSeconds>
              <BatchSize>100</BatchSize>
            </Subscription>
          </DataSource>
        </DataSources>
        <WriteActions>
          <WriteAction ID="WA" TypeID="SystemCenter!Microsoft.EnterpriseManagement.SystemCenter.Subscription.WindowsWorkflowTaskWriteAction">
            <Subscription>
              <VisibleWorkflowStatusUi>true</VisibleWorkflowStatusUi>
              <EnableBatchProcessing>false</EnableBatchProcessing>
              <WindowsWorkflowConfiguration>
                <AssemblyName>Microsoft.EnterpriseManagement.Notifications.Workflows</AssemblyName>
                <WorkflowTypeName>Microsoft.EnterpriseManagement.Notifications.Workflows.SendNotificationsActivity</WorkflowTypeName>
                <WorkflowParameters>
                  <WorkflowParameter Name="SubscriptionId" Type="guid">$MPElement$</WorkflowParameter>
                  <WorkflowParameter Name="DataItem" Type="string">$Data/.$</WorkflowParameter>
                  <WorkflowParameter Name="InstanceId" Type="string">$Data/BaseManagedEntityId$</WorkflowParameter>
                  <WorkflowArrayParameter Name="TemplateIds" Type="string">
                    <Item>5d822e13-666e-d8f6-dd81-ed898a6001ed</Item>
                  </WorkflowArrayParameter>
                  <WorkflowArrayParameter Name="PrimaryUserList" Type="string">
                    <Item>5fb06705-61ca-dc2e-457e-cfdb323daf53</Item>
                  </WorkflowArrayParameter>
                </WorkflowParameters>
                <RetryExceptions />
                <RetryDelaySeconds>60</RetryDelaySeconds>
                <MaximumRunningTimeSeconds>7200</MaximumRunningTimeSeconds>
              </WindowsWorkflowConfiguration>
            </Subscription>
          </WriteAction>
        </WriteActions>
      </Rule>
      <Rule ID="NotificationSubscription0d5244f925c441c7ba20965e7f3ca63e" Enabled="true" Target="Microsoft_SystemCenter_Library!Microsoft.SystemCenter.SubscriptionWorkflowTarget" ConfirmDelivery="true" Remotable="true" Priority="Normal" DiscardLevel="100">
        <Category>System</Category>
        <DataSources>
          <DataSource ID="DS" TypeID="SystemCenter!Microsoft.SystemCenter.CmdbInstanceSubscription.DataSourceModule">
            <Subscription>
              <InstanceSubscription Type="a604b942-4c7b-2fb2-28dc-61dc6f465c68">
                <UpdateInstance>
                  <Criteria>
                    <Expression>
                      <SimpleExpression>
                        <ValueExpression>
                          <Property State="Post">$Context/Property[Type='System_WorkItem_Incident_Library!System.WorkItem.Incident']/Status$</Property>
                        </ValueExpression>
                        <Operator>Equal</Operator>
                        <ValueExpression>
                          <Value>{bd0ae7c4-3315-2eb3-7933-82dfc482dbaf}</Value>
                        </ValueExpression>
                      </SimpleExpression>
                    </Expression>
                  </Criteria>
                </UpdateInstance>
              </InstanceSubscription>
              <PollingIntervalInSeconds>60</PollingIntervalInSeconds>
              <BatchSize>100</BatchSize>
            </Subscription>
          </DataSource>
        </DataSources>
        <WriteActions>
          <WriteAction ID="WA" TypeID="SystemCenter!Microsoft.EnterpriseManagement.SystemCenter.Subscription.WindowsWorkflowTaskWriteAction">
            <Subscription>
              <VisibleWorkflowStatusUi>true</VisibleWorkflowStatusUi>
              <EnableBatchProcessing>false</EnableBatchProcessing>
              <WindowsWorkflowConfiguration>
                <AssemblyName>Microsoft.EnterpriseManagement.Notifications.Workflows</AssemblyName>
                <WorkflowTypeName>Microsoft.EnterpriseManagement.Notifications.Workflows.SendNotificationsActivity</WorkflowTypeName>
                <WorkflowParameters>
                  <WorkflowParameter Name="SubscriptionId" Type="guid">$MPElement$</WorkflowParameter>
                  <WorkflowParameter Name="DataItem" Type="string">$Data/.$</WorkflowParameter>
                  <WorkflowParameter Name="InstanceId" Type="string">$Data/BaseManagedEntityId$</WorkflowParameter>
                  <WorkflowArrayParameter Name="TemplateIds" Type="string">
                    <Item>5d822e13-666e-d8f6-dd81-ed898a6001ed</Item>
                  </WorkflowArrayParameter>
                  <WorkflowArrayParameter Name="PrimaryUserList" Type="string">
                    <Item>5fb06705-61ca-dc2e-457e-cfdb323daf53</Item>
                  </WorkflowArrayParameter>
                </WorkflowParameters>
                <RetryExceptions />
                <RetryDelaySeconds>60</RetryDelaySeconds>
                <MaximumRunningTimeSeconds>7200</MaximumRunningTimeSeconds>
              </WindowsWorkflowConfiguration>
            </Subscription>
          </WriteAction>
        </WriteActions>
      </Rule>
    </Rules>
  </Monitoring>
  <LanguagePacks>
    <LanguagePack ID="ENU" IsDefault="true">
      <DisplayStrings>
        <DisplayString ElementID="WorkItemGroup.3a962c1115fc4c9782510df178aae29c">
          <Name>TestGroup106-SR</Name>
        </DisplayString>
        <DisplayString ElementID="WorkItemGroup.3a962c1115fc4c9782510df178aae29c.Discovery">
          <Name>TestGroup106-SR_Discovery</Name>
          <Description>Discovery for Group TestGroup106-SR</Description>
        </DisplayString>
        <DisplayString ElementID="NotificationSubscription821765ea45df49f282165a0ebba46db7">
          <Name>TestGroup106-IN-C</Name>
        </DisplayString>
        <DisplayString ElementID="NotificationSubscription041ee7779b87404794f2e1f653b3e69c">
          <Name>TestGroup106-IN-U</Name>
        </DisplayString>
        <DisplayString ElementID="NotificationSubscriptioneccb3046f23340ecb29d0e4e750ae44a">
          <Name>TestGroup106-CR-C</Name>
        </DisplayString>
        <DisplayString ElementID="NotificationSubscription487149f2df2b4b80a624ef7229fdc906">
          <Name>TestGroup106-CR-U</Name>
        </DisplayString>
        <DisplayString ElementID="NotificationSubscription1fc97793aaae434789ab2d6c1bec0ee1">
          <Name>TestGroup106-PR-C</Name>
        </DisplayString>
        <DisplayString ElementID="NotificationSubscriptionb6d7290024bb4a31a2aa6efbb708b3c0">
          <Name>TestGroup106-PR-U</Name>
        </DisplayString>
        <DisplayString ElementID="NotificationSubscription680c4416df1741589d5883953e329ad0">
          <Name>TestGroup106-SR-C</Name>
        </DisplayString>
        <DisplayString ElementID="NotificationSubscriptiona11752eb53c44e068e922804724fff19">
          <Name>TestGroup106-SR-U</Name>
        </DisplayString>
        <DisplayString ElementID="NotificationSubscription3ef721c864de4e43aada0ae05786bb89">
          <Name>TestGroup106-SR-U-Completed</Name>
        </DisplayString>
        <DisplayString ElementID="NotificationSubscriptione4e7c2674e4d426fb5ee0a7ede1235a2">
          <Name>TestGroup106-SR-U-Closed</Name>
        </DisplayString>
        <DisplayString ElementID="NotificationSubscription9b34e792a306416099259783ef6febe0">
          <Name>TestGroup106-CR-U-Completed</Name>
        </DisplayString>
        <DisplayString ElementID="NotificationSubscription2226ce77949a44f8a83382b5e66defa0">
          <Name>TestGroup106-CR-U-Closed</Name>
        </DisplayString>
        <DisplayString ElementID="NotificationSubscription55e3a8bf3d75447989c79541aeef8ba9">
          <Name>TestGroup106-IN-U-Resolved</Name>
        </DisplayString>
        <DisplayString ElementID="NotificationSubscription0d5244f925c441c7ba20965e7f3ca63e">
          <Name>TestGroup106-IN-U-Closed</Name>
        </DisplayString>
      </DisplayStrings>
    </LanguagePack>
  </LanguagePacks>
</ManagementPack>